{
  "metadata": {
    "schema_version": "1.0",
    "created_date": "2025-10-18T21:21:36.179903+00:00",
    "curator": "Schema Migration v1.0",
    "source_files": [
      "257.txt",
      "261.txt"
    ],
    "total_entries": 2,
    "description": "Converted from easy_kikuyu_batch_026_conjugations.json",
    "last_updated": "2025-01-08T15:00:00Z"
  },
  "entries": [
    {
      "id": "conj-026-001",
      "english": "Pattern: Subject prefix + -ra- progressive marker + verb stem. Singular (a-): Nĩ aroka (is coming), Nĩ ararĩra (is crying), Nĩ ararĩa (is eating), Nĩ araria (is speaking), Nĩ arakena (is happy), Nĩ aratheka (is laughing), Nĩ arathĩĩ (is going), Nĩ arathooma (is reading), Nĩ arandĩka (is writing). Plural (ma-): Nĩ maroka (are coming), Nĩ mararĩra (are crying), Nĩ mararĩa (are eating), Nĩ mararia (are speaking), Nĩ marakena (are happy), Nĩ maratheka (are laughing), Nĩ marathĩĩ (are going), Nĩ marathooma (are reading), Nĩ marandĩka (are writing)",
      "kikuyu": "3rd Person Present Progressive - Complete",
      "category": "conjugations",
      "difficulty": "intermediate",
      "source": {
        "origin": "Easy Kikuyu Lesson 257",
        "created_date": "2025-01-08",
        "last_updated": "2025-01-08T15:00:00Z"
      },
      "quality": {
        "verified": false,
        "confidence_score": 4.0,
        "source_quality": "community"
      }
    },
    {
      "id": "conj-026-002",
      "english": "1st Person Singular (ndĩ-): Nĩĩ ndĩroka/ndĩrarĩra/ndĩrarĩa/ndĩraria/ndĩrakena/ndĩratheka/ndĩrathĩĩ/ndĩrathooma/ndĩrandĩka (I am coming/crying/eating/speaking/happy/laughing/going/reading/writing). 1st Person Plural (tũ-): Nĩĩ tũroka/tũrarĩra/tũrarĩa/tũraria/tũrakena/tũratheka/tũrathĩĩ/tũrathooma/tũrandĩka (we are...). 2nd Person Singular (ũ-): Nĩĩ ũroka/ũrarĩra/ũrarĩa/ũraria/ũrakena/ũratheka/ũrathĩĩ/ũrathooma/ũrandĩka (you are...). 2nd Person Plural (mũ-): Nĩĩ mũroka/mũrarĩra/mũrarĩa/mũraria/mũrakena/mũratheka/mũrathĩĩ/mũrathooma/mũrandĩka (you all are...)",
      "kikuyu": "1st & 2nd Person Present Progressive",
      "category": "conjugations",
      "difficulty": "intermediate",
      "source": {
        "origin": "Easy Kikuyu Lesson 261",
        "created_date": "2025-01-08",
        "last_updated": "2025-01-08T15:00:00Z"
      },
      "quality": {
        "verified": false,
        "confidence_score": 4.0,
        "source_quality": "community"
      }
    }
  ]
}