{
  "page": 3,
  "totalPages": 7,
  "totalCards": 608,
  "startIndex": 300,
  "endIndex": 399,
  "cards": [
    {
      "id": 1990,
      "english": "proverb containing taha",
      "kikuyu": ", pp. 18–19. Cambridge: Cambridge University Press.",
      "difficulty": "advanced",
      "context": "Traditional proverb featuring the verb 'taha'",
      "cultural_notes": "Traditional Kikuyu proverb from Wiktionary preserving cultural wisdom and linguistic heritage.",
      "quality_score": 4.9,
      "categories": [
        "Traditional Proverbs & Sayings"
      ],
      "has_sub_translations": false
    },
    {
      "id": 1991,
      "english": "proverb containing taha",
      "kikuyu": "Armstrong, Lilias E.",
      "difficulty": "advanced",
      "context": "Traditional proverb featuring the verb 'taha'",
      "cultural_notes": "Traditional Kikuyu proverb from Wiktionary preserving cultural wisdom and linguistic heritage.",
      "quality_score": 4.9,
      "categories": [
        "Traditional Proverbs & Sayings"
      ],
      "has_sub_translations": false
    },
    {
      "id": 1992,
      "english": "proverb containing taha",
      "kikuyu": "The Phonetic and Tonal Structure of Kikuyu",
      "difficulty": "advanced",
      "context": "Traditional proverb featuring the verb 'taha'",
      "cultural_notes": "Traditional Kikuyu proverb from Wiktionary preserving cultural wisdom and linguistic heritage.",
      "quality_score": 4.9,
      "categories": [
        "Traditional Proverbs & Sayings"
      ],
      "has_sub_translations": false
    },
    {
      "id": 1993,
      "english": "proverb containing taha",
      "kikuyu": ", p. 363. Rep. 1967. (Also in",
      "difficulty": "advanced",
      "context": "Traditional proverb featuring the verb 'taha'",
      "cultural_notes": "Traditional Kikuyu proverb from Wiktionary preserving cultural wisdom and linguistic heritage.",
      "quality_score": 4.9,
      "categories": [
        "Traditional Proverbs & Sayings"
      ],
      "has_sub_translations": false
    },
    {
      "id": 1994,
      "english": "proverb containing tema",
      "kikuyu": "gũtema na kanua ti gũtema na rũhiũ",
      "difficulty": "advanced",
      "context": "Traditional proverb featuring the verb 'tema'",
      "cultural_notes": "Traditional Kikuyu proverb from Wiktionary preserving cultural wisdom and linguistic heritage.",
      "quality_score": 4.9,
      "categories": [
        "Traditional Proverbs & Sayings"
      ],
      "has_sub_translations": false
    },
    {
      "id": 1995,
      "english": "proverb containing tema",
      "kikuyu": "Hinde, Hildegarde (1904).",
      "difficulty": "advanced",
      "context": "Traditional proverb featuring the verb 'tema'",
      "cultural_notes": "Traditional Kikuyu proverb from Wiktionary preserving cultural wisdom and linguistic heritage.",
      "quality_score": 4.9,
      "categories": [
        "Traditional Proverbs & Sayings"
      ],
      "has_sub_translations": false
    },
    {
      "id": 1996,
      "english": "proverb containing tema",
      "kikuyu": "Vocabularies of the Kamba and Kikuyu languages of East Africa",
      "difficulty": "advanced",
      "context": "Traditional proverb featuring the verb 'tema'",
      "cultural_notes": "Traditional Kikuyu proverb from Wiktionary preserving cultural wisdom and linguistic heritage.",
      "quality_score": 4.9,
      "categories": [
        "Traditional Proverbs & Sayings"
      ],
      "has_sub_translations": false
    },
    {
      "id": 1997,
      "english": "proverb containing tema",
      "kikuyu": ", pp. 40–41. Cambridge: Cambridge University Press.",
      "difficulty": "advanced",
      "context": "Traditional proverb featuring the verb 'tema'",
      "cultural_notes": "Traditional Kikuyu proverb from Wiktionary preserving cultural wisdom and linguistic heritage.",
      "quality_score": 4.9,
      "categories": [
        "Traditional Proverbs & Sayings"
      ],
      "has_sub_translations": false
    },
    {
      "id": 1998,
      "english": "proverb containing tema",
      "kikuyu": "Armstrong, Lilias E.",
      "difficulty": "advanced",
      "context": "Traditional proverb featuring the verb 'tema'",
      "cultural_notes": "Traditional Kikuyu proverb from Wiktionary preserving cultural wisdom and linguistic heritage.",
      "quality_score": 4.9,
      "categories": [
        "Traditional Proverbs & Sayings"
      ],
      "has_sub_translations": false
    },
    {
      "id": 1999,
      "english": "proverb containing tema",
      "kikuyu": "The Phonetic and Tonal Structure of Kikuyu",
      "difficulty": "advanced",
      "context": "Traditional proverb featuring the verb 'tema'",
      "cultural_notes": "Traditional Kikuyu proverb from Wiktionary preserving cultural wisdom and linguistic heritage.",
      "quality_score": 4.9,
      "categories": [
        "Traditional Proverbs & Sayings"
      ],
      "has_sub_translations": false
    },
    {
      "id": 2000,
      "english": "proverb containing tema",
      "kikuyu": ", p. 363. Rep. 1967. (Also in",
      "difficulty": "advanced",
      "context": "Traditional proverb featuring the verb 'tema'",
      "cultural_notes": "Traditional Kikuyu proverb from Wiktionary preserving cultural wisdom and linguistic heritage.",
      "quality_score": 4.9,
      "categories": [
        "Traditional Proverbs & Sayings"
      ],
      "has_sub_translations": false
    },
    {
      "id": 2001,
      "english": "proverb containing tema",
      "kikuyu": "Barlow, A. Ruffell (1960).",
      "difficulty": "advanced",
      "context": "Traditional proverb featuring the verb 'tema'",
      "cultural_notes": "Traditional Kikuyu proverb from Wiktionary preserving cultural wisdom and linguistic heritage.",
      "quality_score": 4.9,
      "categories": [
        "Traditional Proverbs & Sayings"
      ],
      "has_sub_translations": false
    },
    {
      "id": 2002,
      "english": "proverb containing tema",
      "kikuyu": "Studies in Kikuyu Grammar and Idiom",
      "difficulty": "advanced",
      "context": "Traditional proverb featuring the verb 'tema'",
      "cultural_notes": "Traditional Kikuyu proverb from Wiktionary preserving cultural wisdom and linguistic heritage.",
      "quality_score": 4.9,
      "categories": [
        "Traditional Proverbs & Sayings"
      ],
      "has_sub_translations": false
    },
    {
      "id": 2003,
      "english": "proverb containing theka",
      "kikuyu": "mũrĩa mori yake ndathekagwo",
      "difficulty": "advanced",
      "context": "Traditional proverb featuring the verb 'theka'",
      "cultural_notes": "Traditional Kikuyu proverb from Wiktionary preserving cultural wisdom and linguistic heritage.",
      "quality_score": 4.9,
      "categories": [
        "Traditional Proverbs & Sayings"
      ],
      "has_sub_translations": false
    },
    {
      "id": 2004,
      "english": "proverb containing theka",
      "kikuyu": "rũrĩ itara rũthekaga rũrĩ riko",
      "difficulty": "advanced",
      "context": "Traditional proverb featuring the verb 'theka'",
      "cultural_notes": "Traditional Kikuyu proverb from Wiktionary preserving cultural wisdom and linguistic heritage.",
      "quality_score": 4.9,
      "categories": [
        "Traditional Proverbs & Sayings"
      ],
      "has_sub_translations": false
    },
    {
      "id": 2005,
      "english": "proverb containing theka",
      "kikuyu": "Hinde, Hildegarde (1904).",
      "difficulty": "advanced",
      "context": "Traditional proverb featuring the verb 'theka'",
      "cultural_notes": "Traditional Kikuyu proverb from Wiktionary preserving cultural wisdom and linguistic heritage.",
      "quality_score": 4.9,
      "categories": [
        "Traditional Proverbs & Sayings"
      ],
      "has_sub_translations": false
    },
    {
      "id": 2006,
      "english": "proverb containing theka",
      "kikuyu": "Vocabularies of the Kamba and Kikuyu languages of East Africa",
      "difficulty": "advanced",
      "context": "Traditional proverb featuring the verb 'theka'",
      "cultural_notes": "Traditional Kikuyu proverb from Wiktionary preserving cultural wisdom and linguistic heritage.",
      "quality_score": 4.9,
      "categories": [
        "Traditional Proverbs & Sayings"
      ],
      "has_sub_translations": false
    },
    {
      "id": 2007,
      "english": "proverb containing theka",
      "kikuyu": ", pp. 36–37. Cambridge: Cambridge University Press.",
      "difficulty": "advanced",
      "context": "Traditional proverb featuring the verb 'theka'",
      "cultural_notes": "Traditional Kikuyu proverb from Wiktionary preserving cultural wisdom and linguistic heritage.",
      "quality_score": 4.9,
      "categories": [
        "Traditional Proverbs & Sayings"
      ],
      "has_sub_translations": false
    },
    {
      "id": 2008,
      "english": "proverb containing theka",
      "kikuyu": "Armstrong, Lilias E.",
      "difficulty": "advanced",
      "context": "Traditional proverb featuring the verb 'theka'",
      "cultural_notes": "Traditional Kikuyu proverb from Wiktionary preserving cultural wisdom and linguistic heritage.",
      "quality_score": 4.9,
      "categories": [
        "Traditional Proverbs & Sayings"
      ],
      "has_sub_translations": false
    },
    {
      "id": 2009,
      "english": "proverb containing theka",
      "kikuyu": "The Phonetic and Tonal Structure of Kikuyu",
      "difficulty": "advanced",
      "context": "Traditional proverb featuring the verb 'theka'",
      "cultural_notes": "Traditional Kikuyu proverb from Wiktionary preserving cultural wisdom and linguistic heritage.",
      "quality_score": 4.9,
      "categories": [
        "Traditional Proverbs & Sayings"
      ],
      "has_sub_translations": false
    },
    {
      "id": 2010,
      "english": "proverb containing theka",
      "kikuyu": ", p. 360. Rep. 1967. (Also in",
      "difficulty": "advanced",
      "context": "Traditional proverb featuring the verb 'theka'",
      "cultural_notes": "Traditional Kikuyu proverb from Wiktionary preserving cultural wisdom and linguistic heritage.",
      "quality_score": 4.9,
      "categories": [
        "Traditional Proverbs & Sayings"
      ],
      "has_sub_translations": false
    },
    {
      "id": 2011,
      "english": "proverb containing theka",
      "kikuyu": "Barlow, A. Ruffell (1960).",
      "difficulty": "advanced",
      "context": "Traditional proverb featuring the verb 'theka'",
      "cultural_notes": "Traditional Kikuyu proverb from Wiktionary preserving cultural wisdom and linguistic heritage.",
      "quality_score": 4.9,
      "categories": [
        "Traditional Proverbs & Sayings"
      ],
      "has_sub_translations": false
    },
    {
      "id": 2012,
      "english": "proverb containing theka",
      "kikuyu": "Studies in Kikuyu Grammar and Idiom",
      "difficulty": "advanced",
      "context": "Traditional proverb featuring the verb 'theka'",
      "cultural_notes": "Traditional Kikuyu proverb from Wiktionary preserving cultural wisdom and linguistic heritage.",
      "quality_score": 4.9,
      "categories": [
        "Traditional Proverbs & Sayings"
      ],
      "has_sub_translations": false
    },
    {
      "id": 2013,
      "english": "proverb containing theka",
      "kikuyu": "pp. 90, 238, 247",
      "difficulty": "advanced",
      "context": "Traditional proverb featuring the verb 'theka'",
      "cultural_notes": "Traditional Kikuyu proverb from Wiktionary preserving cultural wisdom and linguistic heritage.",
      "quality_score": 4.9,
      "categories": [
        "Traditional Proverbs & Sayings"
      ],
      "has_sub_translations": false
    },
    {
      "id": 2014,
      "english": "proverb containing theka",
      "kikuyu": "Muiru, David N. (2007).",
      "difficulty": "advanced",
      "context": "Traditional proverb featuring the verb 'theka'",
      "cultural_notes": "Traditional Kikuyu proverb from Wiktionary preserving cultural wisdom and linguistic heritage.",
      "quality_score": 4.9,
      "categories": [
        "Traditional Proverbs & Sayings"
      ],
      "has_sub_translations": false
    },
    {
      "id": 2015,
      "english": "proverb containing theka",
      "kikuyu": "Wĩrute Gĩgĩkũyũ: Marĩtwa Ma Gĩgĩkũyũ Mataũrĩtwo Na Gĩthũngũ",
      "difficulty": "advanced",
      "context": "Traditional proverb featuring the verb 'theka'",
      "cultural_notes": "Traditional Kikuyu proverb from Wiktionary preserving cultural wisdom and linguistic heritage.",
      "quality_score": 4.9,
      "categories": [
        "Traditional Proverbs & Sayings"
      ],
      "has_sub_translations": false
    },
    {
      "id": 2016,
      "english": "proverb containing thiĩ",
      "kikuyu": "gũthiĩ gũtigiragia mũndũ acoke",
      "difficulty": "advanced",
      "context": "Traditional proverb featuring the verb 'thiĩ'",
      "cultural_notes": "Traditional Kikuyu proverb from Wiktionary preserving cultural wisdom and linguistic heritage.",
      "quality_score": 4.9,
      "categories": [
        "Traditional Proverbs & Sayings"
      ],
      "has_sub_translations": false
    },
    {
      "id": 2017,
      "english": "proverb containing thiĩ",
      "kikuyu": "gũthiĩ kuonagia mũndũ njĩra",
      "difficulty": "advanced",
      "context": "Traditional proverb featuring the verb 'thiĩ'",
      "cultural_notes": "Traditional Kikuyu proverb from Wiktionary preserving cultural wisdom and linguistic heritage.",
      "quality_score": 4.9,
      "categories": [
        "Traditional Proverbs & Sayings"
      ],
      "has_sub_translations": false
    },
    {
      "id": 2018,
      "english": "proverb containing thiĩ",
      "kikuyu": "hiti ciathiĩ mbwe ciegangara",
      "difficulty": "advanced",
      "context": "Traditional proverb featuring the verb 'thiĩ'",
      "cultural_notes": "Traditional Kikuyu proverb from Wiktionary preserving cultural wisdom and linguistic heritage.",
      "quality_score": 4.9,
      "categories": [
        "Traditional Proverbs & Sayings"
      ],
      "has_sub_translations": false
    },
    {
      "id": 2019,
      "english": "proverb containing thiĩ",
      "kikuyu": "ngatia ciathiĩ hiti cĩeragara",
      "difficulty": "advanced",
      "context": "Traditional proverb featuring the verb 'thiĩ'",
      "cultural_notes": "Traditional Kikuyu proverb from Wiktionary preserving cultural wisdom and linguistic heritage.",
      "quality_score": 4.9,
      "categories": [
        "Traditional Proverbs & Sayings"
      ],
      "has_sub_translations": false
    },
    {
      "id": 2020,
      "english": "proverb containing thiĩ",
      "kikuyu": "Hinde, Hildegarde (1904).",
      "difficulty": "advanced",
      "context": "Traditional proverb featuring the verb 'thiĩ'",
      "cultural_notes": "Traditional Kikuyu proverb from Wiktionary preserving cultural wisdom and linguistic heritage.",
      "quality_score": 4.9,
      "categories": [
        "Traditional Proverbs & Sayings"
      ],
      "has_sub_translations": false
    },
    {
      "id": 2021,
      "english": "proverb containing thiĩ",
      "kikuyu": "Vocabularies of the Kamba and Kikuyu languages of East Africa",
      "difficulty": "advanced",
      "context": "Traditional proverb featuring the verb 'thiĩ'",
      "cultural_notes": "Traditional Kikuyu proverb from Wiktionary preserving cultural wisdom and linguistic heritage.",
      "quality_score": 4.9,
      "categories": [
        "Traditional Proverbs & Sayings"
      ],
      "has_sub_translations": false
    },
    {
      "id": 2022,
      "english": "proverb containing thiĩ",
      "kikuyu": ", pp. 28–29. Cambridge: Cambridge University Press.",
      "difficulty": "advanced",
      "context": "Traditional proverb featuring the verb 'thiĩ'",
      "cultural_notes": "Traditional Kikuyu proverb from Wiktionary preserving cultural wisdom and linguistic heritage.",
      "quality_score": 4.9,
      "categories": [
        "Traditional Proverbs & Sayings"
      ],
      "has_sub_translations": false
    },
    {
      "id": 2023,
      "english": "proverb containing thiĩ",
      "kikuyu": "Barlow, A. Ruffell (1960).",
      "difficulty": "advanced",
      "context": "Traditional proverb featuring the verb 'thiĩ'",
      "cultural_notes": "Traditional Kikuyu proverb from Wiktionary preserving cultural wisdom and linguistic heritage.",
      "quality_score": 4.9,
      "categories": [
        "Traditional Proverbs & Sayings"
      ],
      "has_sub_translations": false
    },
    {
      "id": 2024,
      "english": "proverb containing thiĩ",
      "kikuyu": "Studies in Kikuyu Grammar and Idiom",
      "difficulty": "advanced",
      "context": "Traditional proverb featuring the verb 'thiĩ'",
      "cultural_notes": "Traditional Kikuyu proverb from Wiktionary preserving cultural wisdom and linguistic heritage.",
      "quality_score": 4.9,
      "categories": [
        "Traditional Proverbs & Sayings"
      ],
      "has_sub_translations": false
    },
    {
      "id": 2025,
      "english": "proverb containing thiĩ",
      "kikuyu": "pp. 99, 238",
      "difficulty": "advanced",
      "context": "Traditional proverb featuring the verb 'thiĩ'",
      "cultural_notes": "Traditional Kikuyu proverb from Wiktionary preserving cultural wisdom and linguistic heritage.",
      "quality_score": 4.9,
      "categories": [
        "Traditional Proverbs & Sayings"
      ],
      "has_sub_translations": false
    },
    {
      "id": 2026,
      "english": "proverb containing tiga",
      "kikuyu": "mũici na kĩhĩĩ atigaga kĩeha kĩarua",
      "difficulty": "advanced",
      "context": "Traditional proverb featuring the verb 'tiga'",
      "cultural_notes": "Traditional Kikuyu proverb from Wiktionary preserving cultural wisdom and linguistic heritage.",
      "quality_score": 4.9,
      "categories": [
        "Traditional Proverbs & Sayings"
      ],
      "has_sub_translations": false
    },
    {
      "id": 2027,
      "english": "proverb containing tiga",
      "kikuyu": "mũici na mũndũ mũka atigaga kĩeha akua",
      "difficulty": "advanced",
      "context": "Traditional proverb featuring the verb 'tiga'",
      "cultural_notes": "Traditional Kikuyu proverb from Wiktionary preserving cultural wisdom and linguistic heritage.",
      "quality_score": 4.9,
      "categories": [
        "Traditional Proverbs & Sayings"
      ],
      "has_sub_translations": false
    },
    {
      "id": 2028,
      "english": "proverb containing tiga",
      "kikuyu": "thĩna ndũtigaga handũ ũramenyera",
      "difficulty": "advanced",
      "context": "Traditional proverb featuring the verb 'tiga'",
      "cultural_notes": "Traditional Kikuyu proverb from Wiktionary preserving cultural wisdom and linguistic heritage.",
      "quality_score": 4.9,
      "categories": [
        "Traditional Proverbs & Sayings"
      ],
      "has_sub_translations": false
    },
    {
      "id": 2029,
      "english": "proverb containing tiga",
      "kikuyu": "Barlow, A. Ruffell (1960).",
      "difficulty": "advanced",
      "context": "Traditional proverb featuring the verb 'tiga'",
      "cultural_notes": "Traditional Kikuyu proverb from Wiktionary preserving cultural wisdom and linguistic heritage.",
      "quality_score": 4.9,
      "categories": [
        "Traditional Proverbs & Sayings"
      ],
      "has_sub_translations": false
    },
    {
      "id": 2030,
      "english": "proverb containing tiga",
      "kikuyu": "Studies in Kikuyu Grammar and Idiom",
      "difficulty": "advanced",
      "context": "Traditional proverb featuring the verb 'tiga'",
      "cultural_notes": "Traditional Kikuyu proverb from Wiktionary preserving cultural wisdom and linguistic heritage.",
      "quality_score": 4.9,
      "categories": [
        "Traditional Proverbs & Sayings"
      ],
      "has_sub_translations": false
    },
    {
      "id": 2031,
      "english": "proverb containing tiga",
      "kikuyu": "Barra, G. (1960).",
      "difficulty": "advanced",
      "context": "Traditional proverb featuring the verb 'tiga'",
      "cultural_notes": "Traditional Kikuyu proverb from Wiktionary preserving cultural wisdom and linguistic heritage.",
      "quality_score": 4.9,
      "categories": [
        "Traditional Proverbs & Sayings"
      ],
      "has_sub_translations": false
    },
    {
      "id": 2032,
      "english": "proverb containing tiga",
      "kikuyu": "1,000 Kikuyu proverbs: with translations and English equivalents",
      "difficulty": "advanced",
      "context": "Traditional proverb featuring the verb 'tiga'",
      "cultural_notes": "Traditional Kikuyu proverb from Wiktionary preserving cultural wisdom and linguistic heritage.",
      "quality_score": 4.9,
      "categories": [
        "Traditional Proverbs & Sayings"
      ],
      "has_sub_translations": false
    },
    {
      "id": 2033,
      "english": "proverb containing tiga",
      "kikuyu": "Armstrong, Lilias E.",
      "difficulty": "advanced",
      "context": "Traditional proverb featuring the verb 'tiga'",
      "cultural_notes": "Traditional Kikuyu proverb from Wiktionary preserving cultural wisdom and linguistic heritage.",
      "quality_score": 4.9,
      "categories": [
        "Traditional Proverbs & Sayings"
      ],
      "has_sub_translations": false
    },
    {
      "id": 2034,
      "english": "proverb containing tiga",
      "kikuyu": "The Phonetic and Tonal Structure of Kikuyu",
      "difficulty": "advanced",
      "context": "Traditional proverb featuring the verb 'tiga'",
      "cultural_notes": "Traditional Kikuyu proverb from Wiktionary preserving cultural wisdom and linguistic heritage.",
      "quality_score": 4.9,
      "categories": [
        "Traditional Proverbs & Sayings"
      ],
      "has_sub_translations": false
    },
    {
      "id": 2035,
      "english": "proverb containing tiga",
      "kikuyu": ", p. 363. Rep. 1967. (Also in",
      "difficulty": "advanced",
      "context": "Traditional proverb featuring the verb 'tiga'",
      "cultural_notes": "Traditional Kikuyu proverb from Wiktionary preserving cultural wisdom and linguistic heritage.",
      "quality_score": 4.9,
      "categories": [
        "Traditional Proverbs & Sayings"
      ],
      "has_sub_translations": false
    },
    {
      "id": 2036,
      "english": "proverb containing tongoria",
      "kikuyu": "ũgĩ ndũtongoragia ta ũrimũ",
      "difficulty": "advanced",
      "context": "Traditional proverb featuring the verb 'tongoria'",
      "cultural_notes": "Traditional Kikuyu proverb from Wiktionary preserving cultural wisdom and linguistic heritage.",
      "quality_score": 4.9,
      "categories": [
        "Traditional Proverbs & Sayings"
      ],
      "has_sub_translations": false
    },
    {
      "id": 2037,
      "english": "proverb containing tongoria",
      "kikuyu": "Armstrong, Lilias E.",
      "difficulty": "advanced",
      "context": "Traditional proverb featuring the verb 'tongoria'",
      "cultural_notes": "Traditional Kikuyu proverb from Wiktionary preserving cultural wisdom and linguistic heritage.",
      "quality_score": 4.9,
      "categories": [
        "Traditional Proverbs & Sayings"
      ],
      "has_sub_translations": false
    },
    {
      "id": 2038,
      "english": "proverb containing tongoria",
      "kikuyu": "The Phonetic and Tonal Structure of Kikuyu",
      "difficulty": "advanced",
      "context": "Traditional proverb featuring the verb 'tongoria'",
      "cultural_notes": "Traditional Kikuyu proverb from Wiktionary preserving cultural wisdom and linguistic heritage.",
      "quality_score": 4.9,
      "categories": [
        "Traditional Proverbs & Sayings"
      ],
      "has_sub_translations": false
    },
    {
      "id": 2039,
      "english": "proverb containing tongoria",
      "kikuyu": ", p. 363. Rep. 1967. (Also in",
      "difficulty": "advanced",
      "context": "Traditional proverb featuring the verb 'tongoria'",
      "cultural_notes": "Traditional Kikuyu proverb from Wiktionary preserving cultural wisdom and linguistic heritage.",
      "quality_score": 4.9,
      "categories": [
        "Traditional Proverbs & Sayings"
      ],
      "has_sub_translations": false
    },
    {
      "id": 2040,
      "english": "proverb containing tongoria",
      "kikuyu": "“tongoria” in Benson, T.G. (1964).",
      "difficulty": "advanced",
      "context": "Traditional proverb featuring the verb 'tongoria'",
      "cultural_notes": "Traditional Kikuyu proverb from Wiktionary preserving cultural wisdom and linguistic heritage.",
      "quality_score": 4.9,
      "categories": [
        "Traditional Proverbs & Sayings"
      ],
      "has_sub_translations": false
    },
    {
      "id": 2041,
      "english": "proverb containing tongoria",
      "kikuyu": ", p. 459. Oxford: Clarendon Press.",
      "difficulty": "advanced",
      "context": "Traditional proverb featuring the verb 'tongoria'",
      "cultural_notes": "Traditional Kikuyu proverb from Wiktionary preserving cultural wisdom and linguistic heritage.",
      "quality_score": 4.9,
      "categories": [
        "Traditional Proverbs & Sayings"
      ],
      "has_sub_translations": false
    },
    {
      "id": 2042,
      "english": "proverb containing tongoria",
      "kikuyu": "Muiru, David N. (2007).",
      "difficulty": "advanced",
      "context": "Traditional proverb featuring the verb 'tongoria'",
      "cultural_notes": "Traditional Kikuyu proverb from Wiktionary preserving cultural wisdom and linguistic heritage.",
      "quality_score": 4.9,
      "categories": [
        "Traditional Proverbs & Sayings"
      ],
      "has_sub_translations": false
    },
    {
      "id": 2043,
      "english": "proverb containing tongoria",
      "kikuyu": "Wĩrute Gĩgĩkũyũ: Marĩtwa Ma Gĩgĩkũyũ Mataũrĩtwo Na Gĩthũngũ",
      "difficulty": "advanced",
      "context": "Traditional proverb featuring the verb 'tongoria'",
      "cultural_notes": "Traditional Kikuyu proverb from Wiktionary preserving cultural wisdom and linguistic heritage.",
      "quality_score": 4.9,
      "categories": [
        "Traditional Proverbs & Sayings"
      ],
      "has_sub_translations": false
    },
    {
      "id": 2044,
      "english": "proverb containing tonya",
      "kikuyu": "mũrimũ ndũrĩ hinya ũgĩtonya mwĩrĩ ta ũkiuma",
      "difficulty": "advanced",
      "context": "Traditional proverb featuring the verb 'tonya'",
      "cultural_notes": "Traditional Kikuyu proverb from Wiktionary preserving cultural wisdom and linguistic heritage.",
      "quality_score": 4.9,
      "categories": [
        "Traditional Proverbs & Sayings"
      ],
      "has_sub_translations": false
    },
    {
      "id": 2045,
      "english": "proverb containing tonya",
      "kikuyu": "“tonya” in Benson, T.G. (1964).",
      "difficulty": "advanced",
      "context": "Traditional proverb featuring the verb 'tonya'",
      "cultural_notes": "Traditional Kikuyu proverb from Wiktionary preserving cultural wisdom and linguistic heritage.",
      "quality_score": 4.9,
      "categories": [
        "Traditional Proverbs & Sayings"
      ],
      "has_sub_translations": false
    },
    {
      "id": 2046,
      "english": "proverb containing tonya",
      "kikuyu": ", p. 460. Oxford: Clarendon Press.",
      "difficulty": "advanced",
      "context": "Traditional proverb featuring the verb 'tonya'",
      "cultural_notes": "Traditional Kikuyu proverb from Wiktionary preserving cultural wisdom and linguistic heritage.",
      "quality_score": 4.9,
      "categories": [
        "Traditional Proverbs & Sayings"
      ],
      "has_sub_translations": false
    },
    {
      "id": 2047,
      "english": "proverb containing tonya",
      "kikuyu": "Armstrong, Lilias E.",
      "difficulty": "advanced",
      "context": "Traditional proverb featuring the verb 'tonya'",
      "cultural_notes": "Traditional Kikuyu proverb from Wiktionary preserving cultural wisdom and linguistic heritage.",
      "quality_score": 4.9,
      "categories": [
        "Traditional Proverbs & Sayings"
      ],
      "has_sub_translations": false
    },
    {
      "id": 2048,
      "english": "proverb containing tonya",
      "kikuyu": "The Phonetic and Tonal Structure of Kikuyu",
      "difficulty": "advanced",
      "context": "Traditional proverb featuring the verb 'tonya'",
      "cultural_notes": "Traditional Kikuyu proverb from Wiktionary preserving cultural wisdom and linguistic heritage.",
      "quality_score": 4.9,
      "categories": [
        "Traditional Proverbs & Sayings"
      ],
      "has_sub_translations": false
    },
    {
      "id": 2049,
      "english": "proverb containing tonya",
      "kikuyu": ", p. 363. Rep. 1967. (Also in",
      "difficulty": "advanced",
      "context": "Traditional proverb featuring the verb 'tonya'",
      "cultural_notes": "Traditional Kikuyu proverb from Wiktionary preserving cultural wisdom and linguistic heritage.",
      "quality_score": 4.9,
      "categories": [
        "Traditional Proverbs & Sayings"
      ],
      "has_sub_translations": false
    },
    {
      "id": 2050,
      "english": "proverb containing tũma",
      "kikuyu": "mũndũ mũka ndatũmagwo thirĩ-inĩ",
      "difficulty": "advanced",
      "context": "Traditional proverb featuring the verb 'tũma'",
      "cultural_notes": "Traditional Kikuyu proverb from Wiktionary preserving cultural wisdom and linguistic heritage.",
      "quality_score": 4.9,
      "categories": [
        "Traditional Proverbs & Sayings"
      ],
      "has_sub_translations": false
    },
    {
      "id": 2051,
      "english": "proverb containing tũma",
      "kikuyu": "Armstrong, Lilias E.",
      "difficulty": "advanced",
      "context": "Traditional proverb featuring the verb 'tũma'",
      "cultural_notes": "Traditional Kikuyu proverb from Wiktionary preserving cultural wisdom and linguistic heritage.",
      "quality_score": 4.9,
      "categories": [
        "Traditional Proverbs & Sayings"
      ],
      "has_sub_translations": false
    },
    {
      "id": 2052,
      "english": "proverb containing tũma",
      "kikuyu": "The Phonetic and Tonal Structure of Kikuyu",
      "difficulty": "advanced",
      "context": "Traditional proverb featuring the verb 'tũma'",
      "cultural_notes": "Traditional Kikuyu proverb from Wiktionary preserving cultural wisdom and linguistic heritage.",
      "quality_score": 4.9,
      "categories": [
        "Traditional Proverbs & Sayings"
      ],
      "has_sub_translations": false
    },
    {
      "id": 2053,
      "english": "proverb containing tũma",
      "kikuyu": ", p. 363. Rep. 1967. (Also in",
      "difficulty": "advanced",
      "context": "Traditional proverb featuring the verb 'tũma'",
      "cultural_notes": "Traditional Kikuyu proverb from Wiktionary preserving cultural wisdom and linguistic heritage.",
      "quality_score": 4.9,
      "categories": [
        "Traditional Proverbs & Sayings"
      ],
      "has_sub_translations": false
    },
    {
      "id": 2054,
      "english": "proverb containing uga",
      "kikuyu": "kĩũra kĩaringio rũũĩ kiugaga nĩkĩo kĩeringia",
      "difficulty": "advanced",
      "context": "Traditional proverb featuring the verb 'uga'",
      "cultural_notes": "Traditional Kikuyu proverb from Wiktionary preserving cultural wisdom and linguistic heritage.",
      "quality_score": 4.9,
      "categories": [
        "Traditional Proverbs & Sayings"
      ],
      "has_sub_translations": false
    },
    {
      "id": 2055,
      "english": "proverb containing uga",
      "kikuyu": "mwagi maguta oigaga atĩ hunyũ nĩ ũmwe na arũme",
      "difficulty": "advanced",
      "context": "Traditional proverb featuring the verb 'uga'",
      "cultural_notes": "Traditional Kikuyu proverb from Wiktionary preserving cultural wisdom and linguistic heritage.",
      "quality_score": 4.9,
      "categories": [
        "Traditional Proverbs & Sayings"
      ],
      "has_sub_translations": false
    },
    {
      "id": 2056,
      "english": "proverb containing uga",
      "kikuyu": ". London: Macmillan.",
      "difficulty": "advanced",
      "context": "Traditional proverb featuring the verb 'uga'",
      "cultural_notes": "Traditional Kikuyu proverb from Wiktionary preserving cultural wisdom and linguistic heritage.",
      "quality_score": 4.9,
      "categories": [
        "Traditional Proverbs & Sayings"
      ],
      "has_sub_translations": false
    },
    {
      "id": 2057,
      "english": "proverb containing uga",
      "kikuyu": "Armstrong, Lilias E.",
      "difficulty": "advanced",
      "context": "Traditional proverb featuring the verb 'uga'",
      "cultural_notes": "Traditional Kikuyu proverb from Wiktionary preserving cultural wisdom and linguistic heritage.",
      "quality_score": 4.9,
      "categories": [
        "Traditional Proverbs & Sayings"
      ],
      "has_sub_translations": false
    },
    {
      "id": 2058,
      "english": "proverb containing uga",
      "kikuyu": "The Phonetic and Tonal Structure of Kikuyu",
      "difficulty": "advanced",
      "context": "Traditional proverb featuring the verb 'uga'",
      "cultural_notes": "Traditional Kikuyu proverb from Wiktionary preserving cultural wisdom and linguistic heritage.",
      "quality_score": 4.9,
      "categories": [
        "Traditional Proverbs & Sayings"
      ],
      "has_sub_translations": false
    },
    {
      "id": 2059,
      "english": "proverb containing uga",
      "kikuyu": ", p. 363. Rep. 1967. (Also in",
      "difficulty": "advanced",
      "context": "Traditional proverb featuring the verb 'uga'",
      "cultural_notes": "Traditional Kikuyu proverb from Wiktionary preserving cultural wisdom and linguistic heritage.",
      "quality_score": 4.9,
      "categories": [
        "Traditional Proverbs & Sayings"
      ],
      "has_sub_translations": false
    },
    {
      "id": 2060,
      "english": "proverb containing uma",
      "kikuyu": "mũrimũ ndũrĩ hinya ũgĩtonya mwĩrĩ ta ũkiuma",
      "difficulty": "advanced",
      "context": "Traditional proverb featuring the verb 'uma'",
      "cultural_notes": "Traditional Kikuyu proverb from Wiktionary preserving cultural wisdom and linguistic heritage.",
      "quality_score": 4.9,
      "categories": [
        "Traditional Proverbs & Sayings"
      ],
      "has_sub_translations": false
    },
    {
      "id": 2061,
      "english": "proverb containing uma",
      "kikuyu": "ngemi ciumaga na mũciĩ",
      "difficulty": "advanced",
      "context": "Traditional proverb featuring the verb 'uma'",
      "cultural_notes": "Traditional Kikuyu proverb from Wiktionary preserving cultural wisdom and linguistic heritage.",
      "quality_score": 4.9,
      "categories": [
        "Traditional Proverbs & Sayings"
      ],
      "has_sub_translations": false
    },
    {
      "id": 2062,
      "english": "proverb containing uma",
      "kikuyu": "ngemi ciumaga ndĩrĩ-inĩ",
      "difficulty": "advanced",
      "context": "Traditional proverb featuring the verb 'uma'",
      "cultural_notes": "Traditional Kikuyu proverb from Wiktionary preserving cultural wisdom and linguistic heritage.",
      "quality_score": 4.9,
      "categories": [
        "Traditional Proverbs & Sayings"
      ],
      "has_sub_translations": false
    },
    {
      "id": 2063,
      "english": "proverb containing uma",
      "kikuyu": "nyũmba na riika itiumagwo",
      "difficulty": "advanced",
      "context": "Traditional proverb featuring the verb 'uma'",
      "cultural_notes": "Traditional Kikuyu proverb from Wiktionary preserving cultural wisdom and linguistic heritage.",
      "quality_score": 4.9,
      "categories": [
        "Traditional Proverbs & Sayings"
      ],
      "has_sub_translations": false
    },
    {
      "id": 2064,
      "english": "proverb containing uma",
      "kikuyu": "wega uumaga na mũciĩ",
      "difficulty": "advanced",
      "context": "Traditional proverb featuring the verb 'uma'",
      "cultural_notes": "Traditional Kikuyu proverb from Wiktionary preserving cultural wisdom and linguistic heritage.",
      "quality_score": 4.9,
      "categories": [
        "Traditional Proverbs & Sayings"
      ],
      "has_sub_translations": false
    },
    {
      "id": 2065,
      "english": "proverb containing ũraga",
      "kikuyu": "kĩara kĩmwe gĩtiũragaga ndaa",
      "difficulty": "advanced",
      "context": "Traditional proverb featuring the verb 'ũraga'",
      "cultural_notes": "Traditional Kikuyu proverb from Wiktionary preserving cultural wisdom and linguistic heritage.",
      "quality_score": 4.9,
      "categories": [
        "Traditional Proverbs & Sayings"
      ],
      "has_sub_translations": false
    },
    {
      "id": 2066,
      "english": "proverb containing ũraga",
      "kikuyu": "kaara kamwe gatiũragaga ndaa",
      "difficulty": "advanced",
      "context": "Traditional proverb featuring the verb 'ũraga'",
      "cultural_notes": "Traditional Kikuyu proverb from Wiktionary preserving cultural wisdom and linguistic heritage.",
      "quality_score": 4.9,
      "categories": [
        "Traditional Proverbs & Sayings"
      ],
      "has_sub_translations": false
    },
    {
      "id": 2067,
      "english": "proverb containing ũraga",
      "kikuyu": "mũ(ũ)ragwo tũhũ ndaregagwo nĩ hiti",
      "difficulty": "advanced",
      "context": "Traditional proverb featuring the verb 'ũraga'",
      "cultural_notes": "Traditional Kikuyu proverb from Wiktionary preserving cultural wisdom and linguistic heritage.",
      "quality_score": 4.9,
      "categories": [
        "Traditional Proverbs & Sayings"
      ],
      "has_sub_translations": false
    },
    {
      "id": 2068,
      "english": "proverb containing ũraga",
      "kikuyu": "mũrimũ wa mũcoka nĩguo ũragaga mũndũ",
      "difficulty": "advanced",
      "context": "Traditional proverb featuring the verb 'ũraga'",
      "cultural_notes": "Traditional Kikuyu proverb from Wiktionary preserving cultural wisdom and linguistic heritage.",
      "quality_score": 4.9,
      "categories": [
        "Traditional Proverbs & Sayings"
      ],
      "has_sub_translations": false
    },
    {
      "id": 2069,
      "english": "proverb containing ũraga",
      "kikuyu": "mũrũngũru wa njamba ũũragaga na ime",
      "difficulty": "advanced",
      "context": "Traditional proverb featuring the verb 'ũraga'",
      "cultural_notes": "Traditional Kikuyu proverb from Wiktionary preserving cultural wisdom and linguistic heritage.",
      "quality_score": 4.9,
      "categories": [
        "Traditional Proverbs & Sayings"
      ],
      "has_sub_translations": false
    },
    {
      "id": 2070,
      "english": "proverb containing ũraga",
      "kikuyu": "Barlow, A. Ruffell (1960).",
      "difficulty": "advanced",
      "context": "Traditional proverb featuring the verb 'ũraga'",
      "cultural_notes": "Traditional Kikuyu proverb from Wiktionary preserving cultural wisdom and linguistic heritage.",
      "quality_score": 4.9,
      "categories": [
        "Traditional Proverbs & Sayings"
      ],
      "has_sub_translations": false
    },
    {
      "id": 2071,
      "english": "proverb containing ũraga",
      "kikuyu": "Studies in Kikuyu Grammar and Idiom",
      "difficulty": "advanced",
      "context": "Traditional proverb featuring the verb 'ũraga'",
      "cultural_notes": "Traditional Kikuyu proverb from Wiktionary preserving cultural wisdom and linguistic heritage.",
      "quality_score": 4.9,
      "categories": [
        "Traditional Proverbs & Sayings"
      ],
      "has_sub_translations": false
    },
    {
      "id": 2072,
      "english": "proverb containing ũraga",
      "kikuyu": "pp. 60, 239",
      "difficulty": "advanced",
      "context": "Traditional proverb featuring the verb 'ũraga'",
      "cultural_notes": "Traditional Kikuyu proverb from Wiktionary preserving cultural wisdom and linguistic heritage.",
      "quality_score": 4.9,
      "categories": [
        "Traditional Proverbs & Sayings"
      ],
      "has_sub_translations": false
    },
    {
      "id": 2073,
      "english": "proverb containing ũria",
      "kikuyu": "kanua karĩa karĩire mbeũ noko",
      "difficulty": "advanced",
      "context": "Traditional proverb featuring the verb 'ũria'",
      "cultural_notes": "Traditional Kikuyu proverb from Wiktionary preserving cultural wisdom and linguistic heritage.",
      "quality_score": 4.9,
      "categories": [
        "Traditional Proverbs & Sayings"
      ],
      "has_sub_translations": false
    },
    {
      "id": 2074,
      "english": "proverb containing ũria",
      "kikuyu": "Armstrong, Lilias E.",
      "difficulty": "advanced",
      "context": "Traditional proverb featuring the verb 'ũria'",
      "cultural_notes": "Traditional Kikuyu proverb from Wiktionary preserving cultural wisdom and linguistic heritage.",
      "quality_score": 4.9,
      "categories": [
        "Traditional Proverbs & Sayings"
      ],
      "has_sub_translations": false
    },
    {
      "id": 2075,
      "english": "proverb containing ũria",
      "kikuyu": "The Phonetic and Tonal Structure of Kikuyu",
      "difficulty": "advanced",
      "context": "Traditional proverb featuring the verb 'ũria'",
      "cultural_notes": "Traditional Kikuyu proverb from Wiktionary preserving cultural wisdom and linguistic heritage.",
      "quality_score": 4.9,
      "categories": [
        "Traditional Proverbs & Sayings"
      ],
      "has_sub_translations": false
    },
    {
      "id": 2076,
      "english": "proverb containing ũria",
      "kikuyu": ", p. 362. Rep. 1967. (Also in",
      "difficulty": "advanced",
      "context": "Traditional proverb featuring the verb 'ũria'",
      "cultural_notes": "Traditional Kikuyu proverb from Wiktionary preserving cultural wisdom and linguistic heritage.",
      "quality_score": 4.9,
      "categories": [
        "Traditional Proverbs & Sayings"
      ],
      "has_sub_translations": false
    },
    {
      "id": 2077,
      "english": "proverb containing ũria",
      "kikuyu": "“ũria” in Benson, T.G. (1964).",
      "difficulty": "advanced",
      "context": "Traditional proverb featuring the verb 'ũria'",
      "cultural_notes": "Traditional Kikuyu proverb from Wiktionary preserving cultural wisdom and linguistic heritage.",
      "quality_score": 4.9,
      "categories": [
        "Traditional Proverbs & Sayings"
      ],
      "has_sub_translations": false
    },
    {
      "id": 2078,
      "english": "proverb containing ũria",
      "kikuyu": ", p. 557. Oxford: Clarendon Press.",
      "difficulty": "advanced",
      "context": "Traditional proverb featuring the verb 'ũria'",
      "cultural_notes": "Traditional Kikuyu proverb from Wiktionary preserving cultural wisdom and linguistic heritage.",
      "quality_score": 4.9,
      "categories": [
        "Traditional Proverbs & Sayings"
      ],
      "has_sub_translations": false
    },
    {
      "id": 2532,
      "english": "a ritual knife does not lack blood",
      "kikuyu": "ithĩnjĩro rĩtiagaga thakame",
      "difficulty": "advanced",
      "context": "Traditional saying about ritual preparation - tools are ready when needed",
      "cultural_notes": "Traditional Kikuyu proverb from Wiktionary sources preserving cultural wisdom and moral teachings. These represent centuries of accumulated knowledge and social values.",
      "quality_score": 4.9,
      "categories": [
        "Wiktionary Proverbs",
        "Cultural Wisdom"
      ],
      "has_sub_translations": false
    },
    {
      "id": 2533,
      "english": "a mouth that has words does not lack something to say",
      "kikuyu": "(kanua) karĩ mata gatiagaga wa kuuga",
      "difficulty": "advanced",
      "context": "About eloquence and having something meaningful to contribute",
      "cultural_notes": "Traditional Kikuyu proverb from Wiktionary sources preserving cultural wisdom and moral teachings. These represent centuries of accumulated knowledge and social values.",
      "quality_score": 4.9,
      "categories": [
        "Wiktionary Proverbs",
        "Cultural Wisdom"
      ],
      "has_sub_translations": false
    },
    {
      "id": 2534,
      "english": "one who walks the earth does not lack a trap",
      "kikuyu": "ng'enda thĩ ndĩagaga mũtegi",
      "difficulty": "advanced",
      "context": "Life is full of obstacles and challenges",
      "cultural_notes": "Traditional Kikuyu proverb from Wiktionary sources preserving cultural wisdom and moral teachings. These represent centuries of accumulated knowledge and social values.",
      "quality_score": 4.9,
      "categories": [
        "Wiktionary Proverbs",
        "Cultural Wisdom"
      ],
      "has_sub_translations": false
    },
    {
      "id": 2535,
      "english": "a communal pot does not lack a stirrer",
      "kikuyu": "nyũngũ ya mũingĩ ndĩagaga mũteng'ũri",
      "difficulty": "advanced",
      "context": "Community work always finds willing hands",
      "cultural_notes": "Traditional Kikuyu proverb from Wiktionary sources preserving cultural wisdom and moral teachings. These represent centuries of accumulated knowledge and social values.",
      "quality_score": 4.9,
      "categories": [
        "Wiktionary Proverbs",
        "Cultural Wisdom"
      ],
      "has_sub_translations": true,
      "sub_translations": [
        {
          "source": "nyũngũ",
          "target": "nyũngũ",
          "position": 0,
          "context": "Pot/cooking vessel"
        },
        {
          "source": "ya",
          "target": "ya",
          "position": 1,
          "context": "Of/belonging to (possessive)"
        },
        {
          "source": "mũingĩ",
          "target": "mũingĩ",
          "position": 2,
          "context": "Many people/community"
        },
        {
          "source": "ndĩagaga",
          "target": "ndĩagaga",
          "position": 3,
          "context": "Does not lack (negative habitual)"
        },
        {
          "source": "mũteng'ũri",
          "target": "mũteng'ũri",
          "position": 4,
          "context": "Stirrer/one who stirs"
        }
      ]
    },
    {
      "id": 2536,
      "english": "there is always a stomach that does not lack",
      "kikuyu": "riko na nda itiagaga",
      "difficulty": "advanced",
      "context": "Someone is always hungry or in need",
      "cultural_notes": "Traditional Kikuyu proverb from Wiktionary sources preserving cultural wisdom and moral teachings. These represent centuries of accumulated knowledge and social values.",
      "quality_score": 4.9,
      "categories": [
        "Wiktionary Proverbs",
        "Cultural Wisdom"
      ],
      "has_sub_translations": false
    },
    {
      "id": 2537,
      "english": "an enemy does not lack a spy",
      "kikuyu": "thũ ndĩagaga mwenji",
      "difficulty": "advanced",
      "context": "Enemies always have informants",
      "cultural_notes": "Traditional Kikuyu proverb from Wiktionary sources preserving cultural wisdom and moral teachings. These represent centuries of accumulated knowledge and social values.",
      "quality_score": 4.9,
      "categories": [
        "Wiktionary Proverbs",
        "Cultural Wisdom"
      ],
      "has_sub_translations": true,
      "sub_translations": [
        {
          "source": "thũ",
          "target": "thũ",
          "position": 0,
          "context": "Enemy"
        },
        {
          "source": "ndĩagaga",
          "target": "ndĩagaga",
          "position": 1,
          "context": "Does not lack"
        },
        {
          "source": "mwenji",
          "target": "mwenji",
          "position": 2,
          "context": "Spy/informant"
        }
      ]
    },
    {
      "id": 2538,
      "english": "a head and hunger do not kill a brave person",
      "kikuyu": "mũtwe na ndaikagia ndahi ndua",
      "difficulty": "advanced",
      "context": "Courage overcomes physical hardships",
      "cultural_notes": "Traditional Kikuyu proverb from Wiktionary sources preserving cultural wisdom and moral teachings. These represent centuries of accumulated knowledge and social values.",
      "quality_score": 4.9,
      "categories": [
        "Wiktionary Proverbs",
        "Cultural Wisdom"
      ],
      "has_sub_translations": false
    },
    {
      "id": 2539,
      "english": "what bears three is increased by its owner",
      "kikuyu": "yaciara mathathatũ yongithagio nĩ mwene",
      "difficulty": "advanced",
      "context": "Good things multiply when properly cared for",
      "cultural_notes": "Traditional Kikuyu proverb from Wiktionary sources preserving cultural wisdom and moral teachings. These represent centuries of accumulated knowledge and social values.",
      "quality_score": 4.9,
      "categories": [
        "Wiktionary Proverbs",
        "Cultural Wisdom"
      ],
      "has_sub_translations": false
    },
    {
      "id": 2540,
      "english": "going leaves room for a person to return",
      "kikuyu": "gũthiĩ gũtigiragia mũndũ acoke",
      "difficulty": "advanced",
      "context": "Departure makes reunion possible",
      "cultural_notes": "Traditional Kikuyu proverb from Wiktionary sources preserving cultural wisdom and moral teachings. These represent centuries of accumulated knowledge and social values.",
      "quality_score": 4.9,
      "categories": [
        "Wiktionary Proverbs",
        "Cultural Wisdom"
      ],
      "has_sub_translations": false
    },
    {
      "id": 2541,
      "english": "a person without goats does not want meat",
      "kikuyu": "mũndũ ũtarĩ mbũri ndendaga nyama",
      "difficulty": "advanced",
      "context": "You appreciate what you don't have",
      "cultural_notes": "Traditional Kikuyu proverb from Wiktionary sources preserving cultural wisdom and moral teachings. These represent centuries of accumulated knowledge and social values.",
      "quality_score": 4.9,
      "categories": [
        "Wiktionary Proverbs",
        "Cultural Wisdom"
      ],
      "has_sub_translations": false
    },
    {
      "id": 2542,
      "english": "the heart eats what it wants",
      "kikuyu": "ngoro ĩrĩĩaga kĩrĩa yenda",
      "difficulty": "advanced",
      "context": "Desires come from within",
      "cultural_notes": "Traditional Kikuyu proverb from Wiktionary sources preserving cultural wisdom and moral teachings. These represent centuries of accumulated knowledge and social values.",
      "quality_score": 4.9,
      "categories": [
        "Wiktionary Proverbs",
        "Cultural Wisdom"
      ],
      "has_sub_translations": true,
      "sub_translations": [
        {
          "source": "ngoro",
          "target": "ngoro",
          "position": 0,
          "context": "Heart"
        },
        {
          "source": "ĩrĩĩaga",
          "target": "ĩrĩĩaga",
          "position": 1,
          "context": "Eats (habitual)"
        },
        {
          "source": "kĩrĩa",
          "target": "kĩrĩa",
          "position": 2,
          "context": "What/that which"
        },
        {
          "source": "yenda",
          "target": "yenda",
          "position": 3,
          "context": "It wants/desires"
        }
      ]
    }
  ]
}