{
  "page": 5,
  "totalPages": 7,
  "totalCards": 692,
  "startIndex": 500,
  "endIndex": 599,
  "cards": [
    {
      "id": 2261,
      "english": "example with kua",
      "kikuyu": ", pp. 18–19. Cambridge: Cambridge University Press",
      "difficulty": "intermediate",
      "context": "Usage example featuring the verb 'kua'",
      "cultural_notes": "Practical usage example from Wiktionary demonstrating natural language patterns.",
      "quality_score": 4.5,
      "categories": [
        "Example Sentences"
      ],
      "has_sub_translations": false
    },
    {
      "id": 2262,
      "english": "example with kua",
      "kikuyu": "Barlow, A. Ruffell (1960)",
      "difficulty": "intermediate",
      "context": "Usage example featuring the verb 'kua'",
      "cultural_notes": "Practical usage example from Wiktionary demonstrating natural language patterns.",
      "quality_score": 4.5,
      "categories": [
        "Example Sentences"
      ],
      "has_sub_translations": false
    },
    {
      "id": 2263,
      "english": "example with kumia",
      "kikuyu": ", p. 362. Rep. 1967. (Also in",
      "difficulty": "intermediate",
      "context": "Usage example featuring the verb 'kumia'",
      "cultural_notes": "Practical usage example from Wiktionary demonstrating natural language patterns.",
      "quality_score": 4.5,
      "categories": [
        "Example Sentences"
      ],
      "has_sub_translations": false
    },
    {
      "id": 2264,
      "english": "example with kundĩka",
      "kikuyu": ", p. 362. Rep. 1967. (Also in",
      "difficulty": "intermediate",
      "context": "Usage example featuring the verb 'kundĩka'",
      "cultural_notes": "Practical usage example from Wiktionary demonstrating natural language patterns.",
      "quality_score": 4.5,
      "categories": [
        "Example Sentences"
      ],
      "has_sub_translations": false
    },
    {
      "id": 2265,
      "english": "example with kundĩka",
      "kikuyu": "“kundĩka” in Benson, T.G. (1964)",
      "difficulty": "intermediate",
      "context": "Usage example featuring the verb 'kundĩka'",
      "cultural_notes": "Practical usage example from Wiktionary demonstrating natural language patterns.",
      "quality_score": 4.5,
      "categories": [
        "Example Sentences"
      ],
      "has_sub_translations": false
    },
    {
      "id": 2267,
      "english": "example with kunya",
      "kikuyu": ", p. 362. Rep. 1967. (Also in",
      "difficulty": "intermediate",
      "context": "Usage example featuring the verb 'kunya'",
      "cultural_notes": "Practical usage example from Wiktionary demonstrating natural language patterns.",
      "quality_score": 4.5,
      "categories": [
        "Example Sentences"
      ],
      "has_sub_translations": false
    },
    {
      "id": 2268,
      "english": "example with kũnja",
      "kikuyu": ", p. 362. Rep. 1967. (Also in",
      "difficulty": "intermediate",
      "context": "Usage example featuring the verb 'kũnja'",
      "cultural_notes": "Practical usage example from Wiktionary demonstrating natural language patterns.",
      "quality_score": 4.5,
      "categories": [
        "Example Sentences"
      ],
      "has_sub_translations": false
    },
    {
      "id": 2269,
      "english": "example with kũya",
      "kikuyu": ", p. 362. Rep. 1967. (Also in",
      "difficulty": "intermediate",
      "context": "Usage example featuring the verb 'kũya'",
      "cultural_notes": "Practical usage example from Wiktionary demonstrating natural language patterns.",
      "quality_score": 4.5,
      "categories": [
        "Example Sentences"
      ],
      "has_sub_translations": false
    },
    {
      "id": 2270,
      "english": "example with maatha",
      "kikuyu": ", p. 362. Rep. 1967. (Also in",
      "difficulty": "intermediate",
      "context": "Usage example featuring the verb 'maatha'",
      "cultural_notes": "Practical usage example from Wiktionary demonstrating natural language patterns.",
      "quality_score": 4.5,
      "categories": [
        "Example Sentences"
      ],
      "has_sub_translations": false
    },
    {
      "id": 2271,
      "english": "example with maatha",
      "kikuyu": "“maatha” in Benson, T.G. (1964)",
      "difficulty": "intermediate",
      "context": "Usage example featuring the verb 'maatha'",
      "cultural_notes": "Practical usage example from Wiktionary demonstrating natural language patterns.",
      "quality_score": 4.5,
      "categories": [
        "Example Sentences"
      ],
      "has_sub_translations": false
    },
    {
      "id": 2272,
      "english": "example with maatha",
      "kikuyu": ", p. 250. Oxford: Clarendon Press",
      "difficulty": "intermediate",
      "context": "Usage example featuring the verb 'maatha'",
      "cultural_notes": "Practical usage example from Wiktionary demonstrating natural language patterns.",
      "quality_score": 4.5,
      "categories": [
        "Example Sentences"
      ],
      "has_sub_translations": false
    },
    {
      "id": 2273,
      "english": "example with mena",
      "kikuyu": "Mugu, Muturi Anthony (2014). \"",
      "difficulty": "intermediate",
      "context": "Usage example featuring the verb 'mena'",
      "cultural_notes": "Practical usage example from Wiktionary demonstrating natural language patterns.",
      "quality_score": 4.5,
      "categories": [
        "Example Sentences"
      ],
      "has_sub_translations": false
    },
    {
      "id": 2274,
      "english": "example with mena",
      "kikuyu": ", p. 362. Rep. 1967. (Also in",
      "difficulty": "intermediate",
      "context": "Usage example featuring the verb 'mena'",
      "cultural_notes": "Practical usage example from Wiktionary demonstrating natural language patterns.",
      "quality_score": 4.5,
      "categories": [
        "Example Sentences"
      ],
      "has_sub_translations": false
    },
    {
      "id": 2275,
      "english": "example with menya",
      "kikuyu": ", pp. 34–35. Cambridge: Cambridge University Press",
      "difficulty": "intermediate",
      "context": "Usage example featuring the verb 'menya'",
      "cultural_notes": "Practical usage example from Wiktionary demonstrating natural language patterns.",
      "quality_score": 4.5,
      "categories": [
        "Example Sentences"
      ],
      "has_sub_translations": false
    },
    {
      "id": 2276,
      "english": "example with menya",
      "kikuyu": "Barlow, A. Ruffell (1960)",
      "difficulty": "intermediate",
      "context": "Usage example featuring the verb 'menya'",
      "cultural_notes": "Practical usage example from Wiktionary demonstrating natural language patterns.",
      "quality_score": 4.5,
      "categories": [
        "Example Sentences"
      ],
      "has_sub_translations": false
    },
    {
      "id": 2277,
      "english": "example with meria",
      "kikuyu": "“meria” in Benson, T.G. (1964)",
      "difficulty": "intermediate",
      "context": "Usage example featuring the verb 'meria'",
      "cultural_notes": "Practical usage example from Wiktionary demonstrating natural language patterns.",
      "quality_score": 4.5,
      "categories": [
        "Example Sentences"
      ],
      "has_sub_translations": false
    },
    {
      "id": 2279,
      "english": "example with noora",
      "kikuyu": ", p. 362. Rep. 1967. (Also in",
      "difficulty": "intermediate",
      "context": "Usage example featuring the verb 'noora'",
      "cultural_notes": "Practical usage example from Wiktionary demonstrating natural language patterns.",
      "quality_score": 4.5,
      "categories": [
        "Example Sentences"
      ],
      "has_sub_translations": false
    },
    {
      "id": 2280,
      "english": "example with nyua",
      "kikuyu": "Barlow, A. Ruffell (1960)",
      "difficulty": "intermediate",
      "context": "Usage example featuring the verb 'nyua'",
      "cultural_notes": "Practical usage example from Wiktionary demonstrating natural language patterns.",
      "quality_score": 4.5,
      "categories": [
        "Example Sentences"
      ],
      "has_sub_translations": false
    },
    {
      "id": 2281,
      "english": "example with nyua",
      "kikuyu": "“nyua” in Benson, T.G. (1964)",
      "difficulty": "intermediate",
      "context": "Usage example featuring the verb 'nyua'",
      "cultural_notes": "Practical usage example from Wiktionary demonstrating natural language patterns.",
      "quality_score": 4.5,
      "categories": [
        "Example Sentences"
      ],
      "has_sub_translations": false
    },
    {
      "id": 2283,
      "english": "example with oha",
      "kikuyu": ", p. 362. Rep. 1967. (Also in",
      "difficulty": "intermediate",
      "context": "Usage example featuring the verb 'oha'",
      "cultural_notes": "Practical usage example from Wiktionary demonstrating natural language patterns.",
      "quality_score": 4.5,
      "categories": [
        "Example Sentences"
      ],
      "has_sub_translations": false
    },
    {
      "id": 2284,
      "english": "example with ona",
      "kikuyu": ", pp. 24–25, 52–53. Cambridge: Cambridge University Press",
      "difficulty": "intermediate",
      "context": "Usage example featuring the verb 'ona'",
      "cultural_notes": "Practical usage example from Wiktionary demonstrating natural language patterns.",
      "quality_score": 4.5,
      "categories": [
        "Example Sentences"
      ],
      "has_sub_translations": false
    },
    {
      "id": 2285,
      "english": "example with ona",
      "kikuyu": ", p. 362. Rep. 1967. (Also in",
      "difficulty": "intermediate",
      "context": "Usage example featuring the verb 'ona'",
      "cultural_notes": "Practical usage example from Wiktionary demonstrating natural language patterns.",
      "quality_score": 4.5,
      "categories": [
        "Example Sentences"
      ],
      "has_sub_translations": false
    },
    {
      "id": 2286,
      "english": "example with ona",
      "kikuyu": "Barlow, A. Ruffell (1960)",
      "difficulty": "intermediate",
      "context": "Usage example featuring the verb 'ona'",
      "cultural_notes": "Practical usage example from Wiktionary demonstrating natural language patterns.",
      "quality_score": 4.5,
      "categories": [
        "Example Sentences"
      ],
      "has_sub_translations": false
    },
    {
      "id": 2287,
      "english": "example with ona",
      "kikuyu": "“ona” in Benson, T.G. (1964)",
      "difficulty": "intermediate",
      "context": "Usage example featuring the verb 'ona'",
      "cultural_notes": "Practical usage example from Wiktionary demonstrating natural language patterns.",
      "quality_score": 4.5,
      "categories": [
        "Example Sentences"
      ],
      "has_sub_translations": false
    },
    {
      "id": 2288,
      "english": "example with ona",
      "kikuyu": ", p. 359. Oxford: Clarendon Press",
      "difficulty": "intermediate",
      "context": "Usage example featuring the verb 'ona'",
      "cultural_notes": "Practical usage example from Wiktionary demonstrating natural language patterns.",
      "quality_score": 4.5,
      "categories": [
        "Example Sentences"
      ],
      "has_sub_translations": false
    },
    {
      "id": 2289,
      "english": "example with onga",
      "kikuyu": ", pp. 56–57. Cambridge: Cambridge University Press",
      "difficulty": "intermediate",
      "context": "Usage example featuring the verb 'onga'",
      "cultural_notes": "Practical usage example from Wiktionary demonstrating natural language patterns.",
      "quality_score": 4.5,
      "categories": [
        "Example Sentences"
      ],
      "has_sub_translations": false
    },
    {
      "id": 2290,
      "english": "example with onga",
      "kikuyu": ", p. 362. Rep. 1967. (Also in",
      "difficulty": "intermediate",
      "context": "Usage example featuring the verb 'onga'",
      "cultural_notes": "Practical usage example from Wiktionary demonstrating natural language patterns.",
      "quality_score": 4.5,
      "categories": [
        "Example Sentences"
      ],
      "has_sub_translations": false
    },
    {
      "id": 2291,
      "english": "example with onia",
      "kikuyu": "“onia” in Benson, T.G. (1964)",
      "difficulty": "intermediate",
      "context": "Usage example featuring the verb 'onia'",
      "cultural_notes": "Practical usage example from Wiktionary demonstrating natural language patterns.",
      "quality_score": 4.5,
      "categories": [
        "Example Sentences"
      ],
      "has_sub_translations": false
    },
    {
      "id": 2292,
      "english": "example with onia",
      "kikuyu": ", p. 359. Oxford: Clarendon Press",
      "difficulty": "intermediate",
      "context": "Usage example featuring the verb 'onia'",
      "cultural_notes": "Practical usage example from Wiktionary demonstrating natural language patterns.",
      "quality_score": 4.5,
      "categories": [
        "Example Sentences"
      ],
      "has_sub_translations": false
    },
    {
      "id": 2293,
      "english": "example with oya",
      "kikuyu": "in “Jogowini dialect” of Kikuyu",
      "difficulty": "intermediate",
      "context": "Usage example featuring the verb 'oya'",
      "cultural_notes": "Practical usage example from Wiktionary demonstrating natural language patterns.",
      "quality_score": 4.5,
      "categories": [
        "Example Sentences"
      ],
      "has_sub_translations": false
    },
    {
      "id": 2294,
      "english": "example with oya",
      "kikuyu": ")] had said that he started off. (lit. it just finished saying so lifted feet.)",
      "difficulty": "intermediate",
      "context": "Usage example featuring the verb 'oya'",
      "cultural_notes": "Practical usage example from Wiktionary demonstrating natural language patterns.",
      "quality_score": 4.5,
      "categories": [
        "Example Sentences"
      ],
      "has_sub_translations": false
    },
    {
      "id": 2295,
      "english": "example with oya",
      "kikuyu": ", pp. 46–47. Cambridge: Cambridge University Press",
      "difficulty": "intermediate",
      "context": "Usage example featuring the verb 'oya'",
      "cultural_notes": "Practical usage example from Wiktionary demonstrating natural language patterns.",
      "quality_score": 4.5,
      "categories": [
        "Example Sentences"
      ],
      "has_sub_translations": false
    },
    {
      "id": 2296,
      "english": "example with oya",
      "kikuyu": "Barlow, A. Ruffell (1960)",
      "difficulty": "intermediate",
      "context": "Usage example featuring the verb 'oya'",
      "cultural_notes": "Practical usage example from Wiktionary demonstrating natural language patterns.",
      "quality_score": 4.5,
      "categories": [
        "Example Sentences"
      ],
      "has_sub_translations": false
    },
    {
      "id": 2297,
      "english": "example with oya",
      "kikuyu": ", pp. 300–301. Rep. 1967. (Also in",
      "difficulty": "intermediate",
      "context": "Usage example featuring the verb 'oya'",
      "cultural_notes": "Practical usage example from Wiktionary demonstrating natural language patterns.",
      "quality_score": 4.5,
      "categories": [
        "Example Sentences"
      ],
      "has_sub_translations": false
    },
    {
      "id": 2298,
      "english": "example with raara",
      "kikuyu": ", p. 362. Rep. 1967. (Also in",
      "difficulty": "intermediate",
      "context": "Usage example featuring the verb 'raara'",
      "cultural_notes": "Practical usage example from Wiktionary demonstrating natural language patterns.",
      "quality_score": 4.5,
      "categories": [
        "Example Sentences"
      ],
      "has_sub_translations": false
    },
    {
      "id": 2299,
      "english": "example with raara",
      "kikuyu": "Barlow, A. Ruffell (1960)",
      "difficulty": "intermediate",
      "context": "Usage example featuring the verb 'raara'",
      "cultural_notes": "Practical usage example from Wiktionary demonstrating natural language patterns.",
      "quality_score": 4.5,
      "categories": [
        "Example Sentences"
      ],
      "has_sub_translations": false
    },
    {
      "id": 2300,
      "english": "example with raaria",
      "kikuyu": "“raaria” in Benson, T.G. (1964)",
      "difficulty": "intermediate",
      "context": "Usage example featuring the verb 'raaria'",
      "cultural_notes": "Practical usage example from Wiktionary demonstrating natural language patterns.",
      "quality_score": 4.5,
      "categories": [
        "Example Sentences"
      ],
      "has_sub_translations": false
    },
    {
      "id": 2301,
      "english": "example with raaria",
      "kikuyu": ", p. 364. Oxford: Clarendon Press",
      "difficulty": "intermediate",
      "context": "Usage example featuring the verb 'raaria'",
      "cultural_notes": "Practical usage example from Wiktionary demonstrating natural language patterns.",
      "quality_score": 4.5,
      "categories": [
        "Example Sentences"
      ],
      "has_sub_translations": false
    },
    {
      "id": 2302,
      "english": "example with raaria",
      "kikuyu": ", p. 362. Rep. 1967. (Also in",
      "difficulty": "intermediate",
      "context": "Usage example featuring the verb 'raaria'",
      "cultural_notes": "Practical usage example from Wiktionary demonstrating natural language patterns.",
      "quality_score": 4.5,
      "categories": [
        "Example Sentences"
      ],
      "has_sub_translations": false
    },
    {
      "id": 2303,
      "english": "example with ragũra",
      "kikuyu": ", p. 362. Rep. 1967. (Also in",
      "difficulty": "intermediate",
      "context": "Usage example featuring the verb 'ragũra'",
      "cultural_notes": "Practical usage example from Wiktionary demonstrating natural language patterns.",
      "quality_score": 4.5,
      "categories": [
        "Example Sentences"
      ],
      "has_sub_translations": false
    },
    {
      "id": 2304,
      "english": "example with ragũra",
      "kikuyu": "“ragũra” in Benson, T.G. (1964)",
      "difficulty": "intermediate",
      "context": "Usage example featuring the verb 'ragũra'",
      "cultural_notes": "Practical usage example from Wiktionary demonstrating natural language patterns.",
      "quality_score": 4.5,
      "categories": [
        "Example Sentences"
      ],
      "has_sub_translations": false
    },
    {
      "id": 2305,
      "english": "example with ragũra",
      "kikuyu": ", p. 366. Oxford: Clarendon Press",
      "difficulty": "intermediate",
      "context": "Usage example featuring the verb 'ragũra'",
      "cultural_notes": "Practical usage example from Wiktionary demonstrating natural language patterns.",
      "quality_score": 4.5,
      "categories": [
        "Example Sentences"
      ],
      "has_sub_translations": false
    },
    {
      "id": 2306,
      "english": "example with a",
      "kikuyu": "“ragũra” in Benson, T.G. (1964)",
      "difficulty": "intermediate",
      "context": "Usage example featuring the verb 'a'",
      "cultural_notes": "Practical usage example from Wiktionary demonstrating natural language patterns.",
      "quality_score": 4.5,
      "categories": [
        "Example Sentences"
      ],
      "has_sub_translations": false
    },
    {
      "id": 2307,
      "english": "example with a",
      "kikuyu": ", p. 366. Oxford: Clarendon Press",
      "difficulty": "intermediate",
      "context": "Usage example featuring the verb 'a'",
      "cultural_notes": "Practical usage example from Wiktionary demonstrating natural language patterns.",
      "quality_score": 4.5,
      "categories": [
        "Example Sentences"
      ],
      "has_sub_translations": false
    },
    {
      "id": 2308,
      "english": "example with rakara",
      "kikuyu": "“rakara” in Benson, T.G. (1964)",
      "difficulty": "intermediate",
      "context": "Usage example featuring the verb 'rakara'",
      "cultural_notes": "Practical usage example from Wiktionary demonstrating natural language patterns.",
      "quality_score": 4.5,
      "categories": [
        "Example Sentences"
      ],
      "has_sub_translations": false
    },
    {
      "id": 2309,
      "english": "example with rakara",
      "kikuyu": ", p. 368. Oxford: Clarendon Press",
      "difficulty": "intermediate",
      "context": "Usage example featuring the verb 'rakara'",
      "cultural_notes": "Practical usage example from Wiktionary demonstrating natural language patterns.",
      "quality_score": 4.5,
      "categories": [
        "Example Sentences"
      ],
      "has_sub_translations": false
    },
    {
      "id": 2310,
      "english": "example with rakara",
      "kikuyu": ", p. 362. Rep. 1967. (Also in",
      "difficulty": "intermediate",
      "context": "Usage example featuring the verb 'rakara'",
      "cultural_notes": "Practical usage example from Wiktionary demonstrating natural language patterns.",
      "quality_score": 4.5,
      "categories": [
        "Example Sentences"
      ],
      "has_sub_translations": false
    },
    {
      "id": 2311,
      "english": "example with ratha",
      "kikuyu": "Rep. 1967. (Also in",
      "difficulty": "intermediate",
      "context": "Usage example featuring the verb 'ratha'",
      "cultural_notes": "Practical usage example from Wiktionary demonstrating natural language patterns.",
      "quality_score": 4.5,
      "categories": [
        "Example Sentences"
      ],
      "has_sub_translations": false
    },
    {
      "id": 2312,
      "english": "example with ratha",
      "kikuyu": "“ratha” in Benson, T.G. (1964)",
      "difficulty": "intermediate",
      "context": "Usage example featuring the verb 'ratha'",
      "cultural_notes": "Practical usage example from Wiktionary demonstrating natural language patterns.",
      "quality_score": 4.5,
      "categories": [
        "Example Sentences"
      ],
      "has_sub_translations": false
    },
    {
      "id": 2314,
      "english": "example with rega",
      "kikuyu": ", pp. 50–51. Cambridge: Cambridge University Press",
      "difficulty": "intermediate",
      "context": "Usage example featuring the verb 'rega'",
      "cultural_notes": "Practical usage example from Wiktionary demonstrating natural language patterns.",
      "quality_score": 4.5,
      "categories": [
        "Example Sentences"
      ],
      "has_sub_translations": false
    },
    {
      "id": 2315,
      "english": "example with rega",
      "kikuyu": ", p. 362. Rep. 1967. (Also in",
      "difficulty": "intermediate",
      "context": "Usage example featuring the verb 'rega'",
      "cultural_notes": "Practical usage example from Wiktionary demonstrating natural language patterns.",
      "quality_score": 4.5,
      "categories": [
        "Example Sentences"
      ],
      "has_sub_translations": false
    },
    {
      "id": 2316,
      "english": "example with rema",
      "kikuyu": ", p. 362. Rep. 1967. (Also in",
      "difficulty": "intermediate",
      "context": "Usage example featuring the verb 'rema'",
      "cultural_notes": "Practical usage example from Wiktionary demonstrating natural language patterns.",
      "quality_score": 4.5,
      "categories": [
        "Example Sentences"
      ],
      "has_sub_translations": false
    },
    {
      "id": 2317,
      "english": "example with remwo",
      "kikuyu": "He who fails to dance the jumping warrior dance attributes his failure to stones on the field",
      "difficulty": "intermediate",
      "context": "Usage example featuring the verb 'remwo'",
      "cultural_notes": "Practical usage example from Wiktionary demonstrating natural language patterns.",
      "quality_score": 4.5,
      "categories": [
        "Example Sentences"
      ],
      "has_sub_translations": false
    },
    {
      "id": 2318,
      "english": "example with remwo",
      "kikuyu": "“rema” in Benson, T.G. (1964)",
      "difficulty": "intermediate",
      "context": "Usage example featuring the verb 'remwo'",
      "cultural_notes": "Practical usage example from Wiktionary demonstrating natural language patterns.",
      "quality_score": 4.5,
      "categories": [
        "Example Sentences"
      ],
      "has_sub_translations": false
    },
    {
      "id": 2320,
      "english": "example with ririkana",
      "kikuyu": ", p. 363. Rep. 1967. (Also in",
      "difficulty": "intermediate",
      "context": "Usage example featuring the verb 'ririkana'",
      "cultural_notes": "Practical usage example from Wiktionary demonstrating natural language patterns.",
      "quality_score": 4.5,
      "categories": [
        "Example Sentences"
      ],
      "has_sub_translations": false
    },
    {
      "id": 2321,
      "english": "example with ririkana",
      "kikuyu": "“ririkana” in Benson, T.G. (1964)",
      "difficulty": "intermediate",
      "context": "Usage example featuring the verb 'ririkana'",
      "cultural_notes": "Practical usage example from Wiktionary demonstrating natural language patterns.",
      "quality_score": 4.5,
      "categories": [
        "Example Sentences"
      ],
      "has_sub_translations": false
    },
    {
      "id": 2322,
      "english": "example with ririkana",
      "kikuyu": ", p. 391. Oxford: Clarendon Press",
      "difficulty": "intermediate",
      "context": "Usage example featuring the verb 'ririkana'",
      "cultural_notes": "Practical usage example from Wiktionary demonstrating natural language patterns.",
      "quality_score": 4.5,
      "categories": [
        "Example Sentences"
      ],
      "has_sub_translations": false
    },
    {
      "id": 2323,
      "english": "example with ririkania",
      "kikuyu": ", p. 363. Rep. 1967. (Also in",
      "difficulty": "intermediate",
      "context": "Usage example featuring the verb 'ririkania'",
      "cultural_notes": "Practical usage example from Wiktionary demonstrating natural language patterns.",
      "quality_score": 4.5,
      "categories": [
        "Example Sentences"
      ],
      "has_sub_translations": false
    },
    {
      "id": 2324,
      "english": "example with ririkania",
      "kikuyu": "“ririkania” in Benson, T.G. (1964)",
      "difficulty": "intermediate",
      "context": "Usage example featuring the verb 'ririkania'",
      "cultural_notes": "Practical usage example from Wiktionary demonstrating natural language patterns.",
      "quality_score": 4.5,
      "categories": [
        "Example Sentences"
      ],
      "has_sub_translations": false
    },
    {
      "id": 2325,
      "english": "example with ririkania",
      "kikuyu": ", p. 391. Oxford: Clarendon Press",
      "difficulty": "intermediate",
      "context": "Usage example featuring the verb 'ririkania'",
      "cultural_notes": "Practical usage example from Wiktionary demonstrating natural language patterns.",
      "quality_score": 4.5,
      "categories": [
        "Example Sentences"
      ],
      "has_sub_translations": false
    },
    {
      "id": 2326,
      "english": "example with rora",
      "kikuyu": ", p. 363. Rep. 1967. (Also in",
      "difficulty": "intermediate",
      "context": "Usage example featuring the verb 'rora'",
      "cultural_notes": "Practical usage example from Wiktionary demonstrating natural language patterns.",
      "quality_score": 4.5,
      "categories": [
        "Example Sentences"
      ],
      "has_sub_translations": false
    },
    {
      "id": 2327,
      "english": "example with rora",
      "kikuyu": "“rora” in Benson, T.G. (1964)",
      "difficulty": "intermediate",
      "context": "Usage example featuring the verb 'rora'",
      "cultural_notes": "Practical usage example from Wiktionary demonstrating natural language patterns.",
      "quality_score": 4.5,
      "categories": [
        "Example Sentences"
      ],
      "has_sub_translations": false
    },
    {
      "id": 2328,
      "english": "example with rora",
      "kikuyu": ", p. 405. Oxford: Clarendon Press",
      "difficulty": "intermediate",
      "context": "Usage example featuring the verb 'rora'",
      "cultural_notes": "Practical usage example from Wiktionary demonstrating natural language patterns.",
      "quality_score": 4.5,
      "categories": [
        "Example Sentences"
      ],
      "has_sub_translations": false
    },
    {
      "id": 2329,
      "english": "example with rota",
      "kikuyu": ", p. 363. Rep. 1967. (Also in",
      "difficulty": "intermediate",
      "context": "Usage example featuring the verb 'rota'",
      "cultural_notes": "Practical usage example from Wiktionary demonstrating natural language patterns.",
      "quality_score": 4.5,
      "categories": [
        "Example Sentences"
      ],
      "has_sub_translations": false
    },
    {
      "id": 2330,
      "english": "example with ruga",
      "kikuyu": ", p. 363. Rep. 1967. (Also in",
      "difficulty": "intermediate",
      "context": "Usage example featuring the verb 'ruga'",
      "cultural_notes": "Practical usage example from Wiktionary demonstrating natural language patterns.",
      "quality_score": 4.5,
      "categories": [
        "Example Sentences"
      ],
      "has_sub_translations": false
    },
    {
      "id": 2331,
      "english": "example with ruma",
      "kikuyu": ", p. 363. Rep. 1967. (Also in",
      "difficulty": "intermediate",
      "context": "Usage example featuring the verb 'ruma'",
      "cultural_notes": "Practical usage example from Wiktionary demonstrating natural language patterns.",
      "quality_score": 4.5,
      "categories": [
        "Example Sentences"
      ],
      "has_sub_translations": false
    },
    {
      "id": 2332,
      "english": "example with ruta",
      "kikuyu": "in “Jogowini dialect” of Kikuyu",
      "difficulty": "intermediate",
      "context": "Usage example featuring the verb 'ruta'",
      "cultural_notes": "Practical usage example from Wiktionary demonstrating natural language patterns.",
      "quality_score": 4.5,
      "categories": [
        "Example Sentences"
      ],
      "has_sub_translations": false
    },
    {
      "id": 2333,
      "english": "example with ruta",
      "kikuyu": ", pp. 58–59. Cambridge: Cambridge University Press",
      "difficulty": "intermediate",
      "context": "Usage example featuring the verb 'ruta'",
      "cultural_notes": "Practical usage example from Wiktionary demonstrating natural language patterns.",
      "quality_score": 4.5,
      "categories": [
        "Example Sentences"
      ],
      "has_sub_translations": false
    },
    {
      "id": 2334,
      "english": "example with ruta",
      "kikuyu": "Barlow, A. Ruffell (1960)",
      "difficulty": "intermediate",
      "context": "Usage example featuring the verb 'ruta'",
      "cultural_notes": "Practical usage example from Wiktionary demonstrating natural language patterns.",
      "quality_score": 4.5,
      "categories": [
        "Example Sentences"
      ],
      "has_sub_translations": false
    },
    {
      "id": 2335,
      "english": "example with ruta",
      "kikuyu": "Wanjohi, G. J. (1997)",
      "difficulty": "intermediate",
      "context": "Usage example featuring the verb 'ruta'",
      "cultural_notes": "Practical usage example from Wiktionary demonstrating natural language patterns.",
      "quality_score": 4.5,
      "categories": [
        "Example Sentences"
      ],
      "has_sub_translations": false
    },
    {
      "id": 2337,
      "english": "example with ruta",
      "kikuyu": ", p. 363. Rep. 1967. (Also in",
      "difficulty": "intermediate",
      "context": "Usage example featuring the verb 'ruta'",
      "cultural_notes": "Practical usage example from Wiktionary demonstrating natural language patterns.",
      "quality_score": 4.5,
      "categories": [
        "Example Sentences"
      ],
      "has_sub_translations": false
    },
    {
      "id": 2338,
      "english": "example with ruta",
      "kikuyu": "“ruta” in Benson, T.G. (1964)",
      "difficulty": "intermediate",
      "context": "Usage example featuring the verb 'ruta'",
      "cultural_notes": "Practical usage example from Wiktionary demonstrating natural language patterns.",
      "quality_score": 4.5,
      "categories": [
        "Example Sentences"
      ],
      "has_sub_translations": false
    },
    {
      "id": 2339,
      "english": "example with ruta",
      "kikuyu": ", pp. 413–414. Oxford: Clarendon Press",
      "difficulty": "intermediate",
      "context": "Usage example featuring the verb 'ruta'",
      "cultural_notes": "Practical usage example from Wiktionary demonstrating natural language patterns.",
      "quality_score": 4.5,
      "categories": [
        "Example Sentences"
      ],
      "has_sub_translations": false
    },
    {
      "id": 2340,
      "english": "example with rĩa",
      "kikuyu": ", p. 362. Rep. 1967. (Also in",
      "difficulty": "intermediate",
      "context": "Usage example featuring the verb 'rĩa'",
      "cultural_notes": "Practical usage example from Wiktionary demonstrating natural language patterns.",
      "quality_score": 4.5,
      "categories": [
        "Example Sentences"
      ],
      "has_sub_translations": false
    },
    {
      "id": 2341,
      "english": "example with rĩa",
      "kikuyu": "Barlow, A. Ruffell (1960)",
      "difficulty": "intermediate",
      "context": "Usage example featuring the verb 'rĩa'",
      "cultural_notes": "Practical usage example from Wiktionary demonstrating natural language patterns.",
      "quality_score": 4.5,
      "categories": [
        "Example Sentences"
      ],
      "has_sub_translations": false
    },
    {
      "id": 2342,
      "english": "example with rĩa",
      "kikuyu": "“rĩa” in Benson, T.G. (1964)",
      "difficulty": "intermediate",
      "context": "Usage example featuring the verb 'rĩa'",
      "cultural_notes": "Practical usage example from Wiktionary demonstrating natural language patterns.",
      "quality_score": 4.5,
      "categories": [
        "Example Sentences"
      ],
      "has_sub_translations": false
    },
    {
      "id": 2344,
      "english": "example with rĩha",
      "kikuyu": ", p. 362. Rep. 1967. (Also in",
      "difficulty": "intermediate",
      "context": "Usage example featuring the verb 'rĩha'",
      "cultural_notes": "Practical usage example from Wiktionary demonstrating natural language patterns.",
      "quality_score": 4.5,
      "categories": [
        "Example Sentences"
      ],
      "has_sub_translations": false
    },
    {
      "id": 2345,
      "english": "example with rĩithia",
      "kikuyu": "“rĩa” in Benson, T.G. (1964)",
      "difficulty": "intermediate",
      "context": "Usage example featuring the verb 'rĩithia'",
      "cultural_notes": "Practical usage example from Wiktionary demonstrating natural language patterns.",
      "quality_score": 4.5,
      "categories": [
        "Example Sentences"
      ],
      "has_sub_translations": false
    },
    {
      "id": 2347,
      "english": "example with rĩma",
      "kikuyu": ", pp. 16–17. Cambridge: Cambridge University Press",
      "difficulty": "intermediate",
      "context": "Usage example featuring the verb 'rĩma'",
      "cultural_notes": "Practical usage example from Wiktionary demonstrating natural language patterns.",
      "quality_score": 4.5,
      "categories": [
        "Example Sentences"
      ],
      "has_sub_translations": false
    },
    {
      "id": 2348,
      "english": "example with rĩma",
      "kikuyu": "Barlow, A. Ruffell (1960)",
      "difficulty": "intermediate",
      "context": "Usage example featuring the verb 'rĩma'",
      "cultural_notes": "Practical usage example from Wiktionary demonstrating natural language patterns.",
      "quality_score": 4.5,
      "categories": [
        "Example Sentences"
      ],
      "has_sub_translations": false
    },
    {
      "id": 2349,
      "english": "example with rĩma",
      "kikuyu": "pp. 32, 236, 243",
      "difficulty": "intermediate",
      "context": "Usage example featuring the verb 'rĩma'",
      "cultural_notes": "Practical usage example from Wiktionary demonstrating natural language patterns.",
      "quality_score": 4.5,
      "categories": [
        "Example Sentences"
      ],
      "has_sub_translations": false
    },
    {
      "id": 2350,
      "english": "example with rĩma",
      "kikuyu": ", p. 362. Rep. 1967. (Also in",
      "difficulty": "intermediate",
      "context": "Usage example featuring the verb 'rĩma'",
      "cultural_notes": "Practical usage example from Wiktionary demonstrating natural language patterns.",
      "quality_score": 4.5,
      "categories": [
        "Example Sentences"
      ],
      "has_sub_translations": false
    },
    {
      "id": 2351,
      "english": "example with rĩra",
      "kikuyu": ", pp. 16–7. Cambridge: Cambridge University Press",
      "difficulty": "intermediate",
      "context": "Usage example featuring the verb 'rĩra'",
      "cultural_notes": "Practical usage example from Wiktionary demonstrating natural language patterns.",
      "quality_score": 4.5,
      "categories": [
        "Example Sentences"
      ],
      "has_sub_translations": false
    },
    {
      "id": 2352,
      "english": "example with rĩra",
      "kikuyu": ", p. 362. Rep. 1967. (Also in",
      "difficulty": "intermediate",
      "context": "Usage example featuring the verb 'rĩra'",
      "cultural_notes": "Practical usage example from Wiktionary demonstrating natural language patterns.",
      "quality_score": 4.5,
      "categories": [
        "Example Sentences"
      ],
      "has_sub_translations": false
    },
    {
      "id": 2353,
      "english": "example with rũgama",
      "kikuyu": "in “Jogowini dialect” of Kikuyu",
      "difficulty": "intermediate",
      "context": "Usage example featuring the verb 'rũgama'",
      "cultural_notes": "Practical usage example from Wiktionary demonstrating natural language patterns.",
      "quality_score": 4.5,
      "categories": [
        "Example Sentences"
      ],
      "has_sub_translations": false
    },
    {
      "id": 2354,
      "english": "example with rũgama",
      "kikuyu": ", pp. 56–57. Cambridge: Cambridge University Press",
      "difficulty": "intermediate",
      "context": "Usage example featuring the verb 'rũgama'",
      "cultural_notes": "Practical usage example from Wiktionary demonstrating natural language patterns.",
      "quality_score": 4.5,
      "categories": [
        "Example Sentences"
      ],
      "has_sub_translations": false
    },
    {
      "id": 2355,
      "english": "example with rũgama",
      "kikuyu": "“rũgama” in Benson, T.G. (1964)",
      "difficulty": "intermediate",
      "context": "Usage example featuring the verb 'rũgama'",
      "cultural_notes": "Practical usage example from Wiktionary demonstrating natural language patterns.",
      "quality_score": 4.5,
      "categories": [
        "Example Sentences"
      ],
      "has_sub_translations": false
    },
    {
      "id": 2356,
      "english": "example with rũgama",
      "kikuyu": ", p. 416. Oxford: Clarendon Press",
      "difficulty": "intermediate",
      "context": "Usage example featuring the verb 'rũgama'",
      "cultural_notes": "Practical usage example from Wiktionary demonstrating natural language patterns.",
      "quality_score": 4.5,
      "categories": [
        "Example Sentences"
      ],
      "has_sub_translations": false
    },
    {
      "id": 2357,
      "english": "example with rũgama",
      "kikuyu": ", p. 363. Rep. 1967. (Also in",
      "difficulty": "intermediate",
      "context": "Usage example featuring the verb 'rũgama'",
      "cultural_notes": "Practical usage example from Wiktionary demonstrating natural language patterns.",
      "quality_score": 4.5,
      "categories": [
        "Example Sentences"
      ],
      "has_sub_translations": false
    },
    {
      "id": 2358,
      "english": "example with rũma",
      "kikuyu": ", p. 363. Rep. 1967. (Also in",
      "difficulty": "intermediate",
      "context": "Usage example featuring the verb 'rũma'",
      "cultural_notes": "Practical usage example from Wiktionary demonstrating natural language patterns.",
      "quality_score": 4.5,
      "categories": [
        "Example Sentences"
      ],
      "has_sub_translations": false
    },
    {
      "id": 2359,
      "english": "example with rũmĩrĩra",
      "kikuyu": ", p. 363. Rep. 1967. (Also in",
      "difficulty": "intermediate",
      "context": "Usage example featuring the verb 'rũmĩrĩra'",
      "cultural_notes": "Practical usage example from Wiktionary demonstrating natural language patterns.",
      "quality_score": 4.5,
      "categories": [
        "Example Sentences"
      ],
      "has_sub_translations": false
    },
    {
      "id": 2360,
      "english": "example with rũũga",
      "kikuyu": ", pp. 34–35. Cambridge: Cambridge University Press",
      "difficulty": "intermediate",
      "context": "Usage example featuring the verb 'rũũga'",
      "cultural_notes": "Practical usage example from Wiktionary demonstrating natural language patterns.",
      "quality_score": 4.5,
      "categories": [
        "Example Sentences"
      ],
      "has_sub_translations": false
    },
    {
      "id": 2361,
      "english": "example with rũũga",
      "kikuyu": ", p. 363. Rep. 1967. (Also in",
      "difficulty": "intermediate",
      "context": "Usage example featuring the verb 'rũũga'",
      "cultural_notes": "Practical usage example from Wiktionary demonstrating natural language patterns.",
      "quality_score": 4.5,
      "categories": [
        "Example Sentences"
      ],
      "has_sub_translations": false
    },
    {
      "id": 2362,
      "english": "example with rũũga",
      "kikuyu": "“rũũga” in Benson, T.G. (1964)",
      "difficulty": "intermediate",
      "context": "Usage example featuring the verb 'rũũga'",
      "cultural_notes": "Practical usage example from Wiktionary demonstrating natural language patterns.",
      "quality_score": 4.5,
      "categories": [
        "Example Sentences"
      ],
      "has_sub_translations": false
    },
    {
      "id": 2364,
      "english": "example with taara",
      "kikuyu": ", p. 363. Rep. 1967. (Also in",
      "difficulty": "intermediate",
      "context": "Usage example featuring the verb 'taara'",
      "cultural_notes": "Practical usage example from Wiktionary demonstrating natural language patterns.",
      "quality_score": 4.5,
      "categories": [
        "Example Sentences"
      ],
      "has_sub_translations": false
    },
    {
      "id": 2365,
      "english": "example with taara",
      "kikuyu": "“taara” in Benson, T.G. (1964)",
      "difficulty": "intermediate",
      "context": "Usage example featuring the verb 'taara'",
      "cultural_notes": "Practical usage example from Wiktionary demonstrating natural language patterns.",
      "quality_score": 4.5,
      "categories": [
        "Example Sentences"
      ],
      "has_sub_translations": false
    },
    {
      "id": 2367,
      "english": "example with taha",
      "kikuyu": ", pp. 18–19. Cambridge: Cambridge University Press",
      "difficulty": "intermediate",
      "context": "Usage example featuring the verb 'taha'",
      "cultural_notes": "Practical usage example from Wiktionary demonstrating natural language patterns.",
      "quality_score": 4.5,
      "categories": [
        "Example Sentences"
      ],
      "has_sub_translations": false
    },
    {
      "id": 2368,
      "english": "example with taha",
      "kikuyu": ", p. 363. Rep. 1967. (Also in",
      "difficulty": "intermediate",
      "context": "Usage example featuring the verb 'taha'",
      "cultural_notes": "Practical usage example from Wiktionary demonstrating natural language patterns.",
      "quality_score": 4.5,
      "categories": [
        "Example Sentences"
      ],
      "has_sub_translations": false
    },
    {
      "id": 2369,
      "english": "example with tahĩka",
      "kikuyu": "“taha” in Benson, T.G. (1964)",
      "difficulty": "intermediate",
      "context": "Usage example featuring the verb 'tahĩka'",
      "cultural_notes": "Practical usage example from Wiktionary demonstrating natural language patterns.",
      "quality_score": 4.5,
      "categories": [
        "Example Sentences"
      ],
      "has_sub_translations": false
    },
    {
      "id": 2371,
      "english": "example with te",
      "kikuyu": "in the “Jogowini dialect” of Kikuyu",
      "difficulty": "intermediate",
      "context": "Usage example featuring the verb 'te'",
      "cultural_notes": "Practical usage example from Wiktionary demonstrating natural language patterns.",
      "quality_score": 4.5,
      "categories": [
        "Example Sentences"
      ],
      "has_sub_translations": false
    }
  ]
}