{
  "batch_info": {
    "batch_number": "020",
    "total_cards": 19,
    "category": "phrases",
    "source_files": ["195.txt", "198.txt", "204.txt"],
    "created_date": "2025-01-08",
    "last_updated": "2025-01-09T13:15:00Z"
  },
  "flashcards": [
    {
      "id": "phrase-020-001",
      "kikuyu": "Njeri wa Njoroge",
      "english": "Njeri daughter of Njoroge",
      "category": "phrases",
      "difficulty": "beginner",
      "notes": "Response to lineage inquiry. Pattern: [name] wa [father's name]",
      "quality_score": 4.7,
      "source": {
        "origin": "Easy Kikuyu Lesson 195",
        "created_date": "2025-01-08",
        "last_updated": "2025-01-09T13:15:00Z"
      }
    },
    {
      "id": "phrase-020-002",
      "kikuyu": "Nĩĩ ndainuka",
      "english": "I am off home / I'm leaving now",
      "category": "phrases",
      "difficulty": "beginner",
      "notes": "Departure announcement. 'ndainuka' = I am getting up/leaving",
      "quality_score": 4.6,
      "source": {
        "origin": "Easy Kikuyu Lesson 195",
        "created_date": "2025-01-08",
        "last_updated": "2025-01-09T13:15:00Z"
      }
    },
    {
      "id": "phrase-020-003",
      "kikuyu": "Mũirĩtu ũyũ",
      "english": "This girl",
      "category": "phrases",
      "difficulty": "beginner",
      "notes": "Demonstrative phrase. 'ũyũ' = this one (singular)",
      "quality_score": 4.4,
      "source": {
        "origin": "Easy Kikuyu Lesson 198",
        "created_date": "2025-01-08",
        "last_updated": "2025-01-09T13:15:00Z"
      }
    },
    {
      "id": "phrase-020-004",
      "kikuyu": "Aĩrĩtu aya",
      "english": "These girls",
      "category": "phrases",
      "difficulty": "beginner",
      "notes": "Demonstrative phrase. 'aya' = these ones (plural)",
      "quality_score": 4.4,
      "source": {
        "origin": "Easy Kikuyu Lesson 198",
        "created_date": "2025-01-08",
        "last_updated": "2025-01-09T13:15:00Z"
      }
    },
    {
      "id": "phrase-020-005",
      "kikuyu": "Ũyũ nũũ?",
      "english": "Who is this?",
      "category": "phrases",
      "difficulty": "beginner",
      "notes": "Identification question. Singular form",
      "quality_score": 4.5,
      "source": {
        "origin": "Easy Kikuyu Lesson 198",
        "created_date": "2025-01-08",
        "last_updated": "2025-01-09T13:15:00Z"
      }
    },
    {
      "id": "phrase-020-006",
      "kikuyu": "Aya nĩ a?",
      "english": "Who are these?",
      "category": "phrases",
      "difficulty": "beginner",
      "notes": "Identification question. Plural form",
      "quality_score": 4.5,
      "source": {
        "origin": "Easy Kikuyu Lesson 198",
        "created_date": "2025-01-08",
        "last_updated": "2025-01-09T13:15:00Z"
      }
    },
    {
      "id": "phrase-020-007",
      "kikuyu": "Etagwo atĩa?",
      "english": "What is his/her name?",
      "category": "phrases",
      "difficulty": "beginner",
      "notes": "Name inquiry. Literally 'He/she is called what?'",
      "quality_score": 4.6,
      "source": {
        "origin": "Easy Kikuyu Lesson 198",
        "created_date": "2025-01-08",
        "last_updated": "2025-01-09T13:15:00Z"
      }
    },
    {
      "id": "phrase-020-008",
      "kikuyu": "Nĩ waragia gĩkũyũ?",
      "english": "Do you speak Kikuyu?",
      "category": "phrases",
      "difficulty": "beginner",
      "notes": "Language ability question. 'waragia' = you speak",
      "quality_score": 4.7,
      "source": {
        "origin": "Easy Kikuyu Lesson 198",
        "created_date": "2025-01-08",
        "last_updated": "2025-01-09T13:15:00Z"
      }
    },
    {
      "id": "phrase-020-009",
      "kikuyu": "Aria na nĩĩ",
      "english": "Speak to me / Talk with me",
      "category": "phrases",
      "difficulty": "beginner",
      "notes": "Request to speak. 'Aria' = speak, 'na nĩĩ' = with me",
      "quality_score": 4.5,
      "source": {
        "origin": "Easy Kikuyu Lesson 198",
        "created_date": "2025-01-08",
        "last_updated": "2025-01-09T13:15:00Z"
      }
    },
    {
      "id": "phrase-020-010",
      "kikuyu": "Nĩĩtũcemanie",
      "english": "Let's meet",
      "category": "phrases",
      "difficulty": "intermediate",
      "notes": "Meeting suggestion. Subjunctive form",
      "quality_score": 4.8,
      "source": {
        "origin": "Easy Kikuyu Lesson 204",
        "created_date": "2025-01-08",
        "last_updated": "2025-01-09T13:15:00Z"
      }
    },
    {
      "id": "phrase-020-011",
      "kikuyu": "Ũkwenda tũcemanie kũ?",
      "english": "Where do you want us to meet?",
      "category": "phrases",
      "difficulty": "intermediate",
      "notes": "Meeting location question. 'ũkwenda' = you want",
      "quality_score": 4.8,
      "source": {
        "origin": "Easy Kikuyu Lesson 204",
        "created_date": "2025-01-08",
        "last_updated": "2025-01-09T13:15:00Z"
      }
    },
    {
      "id": "phrase-020-012",
      "kikuyu": "Nĩ tũcemanie mũkawainĩ",
      "english": "Let us meet at a hotel",
      "category": "phrases",
      "difficulty": "intermediate",
      "notes": "Meeting place suggestion. 'mũkawainĩ' = at a hotel",
      "quality_score": 4.7,
      "source": {
        "origin": "Easy Kikuyu Lesson 204",
        "created_date": "2025-01-08",
        "last_updated": "2025-01-09T13:15:00Z"
      }
    },
    {
      "id": "phrase-020-013",
      "kikuyu": "Mũkawa ũrikũ?",
      "english": "Which hotel?",
      "category": "phrases",
      "difficulty": "beginner",
      "notes": "Specification question. 'ũrikũ' = which one?",
      "quality_score": 4.6,
      "source": {
        "origin": "Easy Kikuyu Lesson 204",
        "created_date": "2025-01-08",
        "last_updated": "2025-01-09T13:15:00Z"
      }
    },
    {
      "id": "phrase-020-014",
      "kikuyu": "Ndiũĩ",
      "english": "I don't know it",
      "category": "phrases",
      "difficulty": "beginner",
      "notes": "Negative knowledge statement. 'ũĩ' = you know",
      "quality_score": 4.5,
      "source": {
        "origin": "Easy Kikuyu Lesson 204",
        "created_date": "2025-01-08",
        "last_updated": "2025-01-09T13:15:00Z"
      }
    },
    {
      "id": "phrase-020-015",
      "kikuyu": "Haica matatu ya taũnĩ",
      "english": "Board a matatu to town",
      "category": "phrases",
      "difficulty": "intermediate",
      "notes": "Transportation direction. 'matatu' = minibus, 'haica' = board/climb",
      "quality_score": 4.8,
      "source": {
        "origin": "Easy Kikuyu Lesson 204",
        "created_date": "2025-01-08",
        "last_updated": "2025-01-09T13:15:00Z"
      }
    },
    {
      "id": "phrase-020-016",
      "kikuyu": "Wakinĩya ũhũrĩre thimũ",
      "english": "When you arrive call me by phone",
      "category": "phrases",
      "difficulty": "intermediate",
      "notes": "Instruction with temporal clause. 'wakinĩya' = when you arrive",
      "quality_score": 4.8,
      "source": {
        "origin": "Easy Kikuyu Lesson 204",
        "created_date": "2025-01-08",
        "last_updated": "2025-01-09T13:15:00Z"
      }
    },
    {
      "id": "phrase-020-017",
      "kikuyu": "Taũnĩ nĩ nene",
      "english": "The town is large",
      "category": "phrases",
      "difficulty": "beginner",
      "notes": "Descriptive statement. 'nene' = big/large",
      "quality_score": 4.6,
      "source": {
        "origin": "Easy Kikuyu Lesson 204",
        "created_date": "2025-01-08",
        "last_updated": "2025-01-09T13:15:00Z"
      }
    },
    {
      "id": "phrase-020-018",
      "kikuyu": "Ngumĩra kũ?",
      "english": "Where do I disembark?",
      "category": "phrases",
      "difficulty": "intermediate",
      "notes": "Transportation question. 'ngumĩra' = I disembark/alight",
      "quality_score": 4.7,
      "source": {
        "origin": "Easy Kikuyu Lesson 204",
        "created_date": "2025-01-08",
        "last_updated": "2025-01-09T13:15:00Z"
      }
    },
    {
      "id": "phrase-020-019",
      "kikuyu": "Ũmĩra bothita",
      "english": "Disembark at Posta / Post office",
      "category": "phrases",
      "difficulty": "intermediate",
      "notes": "Transportation direction. 'bothita' = post office",
      "quality_score": 4.7,
      "source": {
        "origin": "Easy Kikuyu Lesson 204",
        "created_date": "2025-01-08",
        "last_updated": "2025-01-09T13:15:00Z"
      }
    }
  ]
}
